[{"id_val":"9NNUXQPBUvM","cid":"UgySqFYWVaeVVid9F-54AaABAg","text":"Trackname at 6:22 ? Please ans thanks","time":"8 months ago","author":"R. LAMBOLEY","channel":"UCTMvyinCW8GI7U6uVHqcsGg","votes":"0","photo":"https:\/\/yt3.ggpht.com\/ytc\/AKedOLRPq3c3B7HSbvdxGlRownloXXYeMxN2rwiO6Q=s176-c-k-c0x00ffffff-no-rj","heart":false},{"id_val":"9NNUXQPBUvM","cid":"UgymWeDDIP7S0ioeKRB4AaABAg","text":"15:38","time":"8 months ago","author":"Kieran Evans","channel":"UCOXlfDpk45e7gMY32RAnnhw","votes":"2","photo":"https:\/\/yt3.ggpht.com\/ytc\/AKedOLTwldnDNPfs5sWiJfrqhRi6Zy73MniFG2wcP4zuyA=s176-c-k-c0x00ffffff-no-rj","heart":false}]