[{"id_val":"bmJqPnV3Jrw","cid":"UgjlxTemGWmORngCoAEC.899lo3Hiddr8C00_R61-J5","text":"1:20 anyone? please!?","time":"5 years ago","author":"Ryan Collins","channel":"UCu_5Q33idc98GHPZ9HFlHgg","votes":"0","photo":"https:\/\/yt3.ggpht.com\/ytc\/AKedOLQI-10G7rs-fmtsMmscPkW2halNKYcfYQ4RxQ=s176-c-k-c0x00ffffff-no-rj","heart":false},{"id_val":"bmJqPnV3Jrw","cid":"UgjlxTemGWmORngCoAEC.899lo3Hiddr8GFORrj_Kx3","text":"1:20:00 - Joel Alter - Everlasting (remix by Dorisburg)","time":"5 years ago","author":"fitty77","channel":"UCaBxpunrJynQDZRCLK_-m0Q","votes":"3","photo":"https:\/\/yt3.ggpht.com\/ytc\/AKedOLRxZOAVgw0KbzzqIddXCnCnawNI2iS9jRezcapoZa4=s176-c-k-c0x00ffffff-no-rj","heart":false},{"id_val":"bmJqPnV3Jrw","cid":"UgjlxTemGWmORngCoAEC.899lo3Hiddr8JVNrtuA5bD","text":"Track @ 132: Orlando Voorn-Gain Upwards (ROD rmx)","time":"5 years ago","author":"attickdog","channel":"UC0Nf9TOWgafk1NxB6WVSl_g","votes":"2","photo":"https:\/\/yt3.ggpht.com\/ytc\/AKedOLSsDxBEfMY2e6gf7nuA2DmPwyzxXGYhEvyVZw=s176-c-k-c0x00ffffff-no-rj","heart":false},{"id_val":"bmJqPnV3Jrw","cid":"UgjlxTemGWmORngCoAEC.899lo3Hiddr8JVOKASU2tj","text":"Track @ 132: Orlando Voorn-Gain Upwards (ROD rmx)","time":"5 years ago","author":"attickdog","channel":"UC0Nf9TOWgafk1NxB6WVSl_g","votes":"2","photo":"https:\/\/yt3.ggpht.com\/ytc\/AKedOLSsDxBEfMY2e6gf7nuA2DmPwyzxXGYhEvyVZw=s176-c-k-c0x00ffffff-no-rj","heart":false},{"id_val":"bmJqPnV3Jrw","cid":"UgjlxTemGWmORngCoAEC.899lo3Hiddr9430Qw9oInY","text":"77:00 The Junkies - Living and Giving","time":"1 year ago","author":"Robb Pastor","channel":"UClYwgOK8o5ipHE2SNYiy9LA","votes":"0","photo":"https:\/\/yt3.ggpht.com\/ytc\/AKedOLS3xj8u9iVSoJZU13nkCu_OPuO7szJ9Un2H7A=s176-c-k-c0x00ffffff-no-rj","heart":false},{"id_val":"bmJqPnV3Jrw","cid":"UgyDNTxJfx5iyrpyYJ54AaABAg","text":"22:00 - 30:00 ====> Gosh what a tune...this is amazing!","time":"3 years ago","author":"Connor Sandle","channel":"UCPWLNhrJBuVufjsZW3CD23w","votes":"2","photo":"https:\/\/yt3.ggpht.com\/ytc\/AKedOLSGffLYq0bDR8FmzipOVDveM0fWtSnlcOfu8Q=s176-c-k-c0x00ffffff-no-rj","heart":false},{"id_val":"bmJqPnV3Jrw","cid":"UgyfJkLIlB37QTesucl4AaABAg","text":"1:15 is just pure vibessss","time":"3 years ago","author":"Rohan Sable","channel":"UCceYhZklhaxnPaxYJh7Y_dw","votes":"0","photo":"https:\/\/yt3.ggpht.com\/ytc\/AKedOLS6bO4pMT8i_YjutHueHv6kHnbQdP6C1f5SdYwXCA=s176-c-k-c0x00ffffff-no-rj","heart":false},{"id_val":"bmJqPnV3Jrw","cid":"UgyGBkkve-9QAlIuOr94AaABAg","text":"1:05:30 braaavooo !!\nMaestro \u2661\u2606\u2661\u2606","time":"2 years ago","author":"Johncr777","channel":"UC-dq78be6wUM5M_q1X6Xdug","votes":"0","photo":"https:\/\/yt3.ggpht.com\/ytc\/AKedOLT0dWL-vzWOHEmtCpu_35F5wg297V9MUhNaSt3P4g=s176-c-k-c0x00ffffff-no-rj","heart":false},{"id_val":"bmJqPnV3Jrw","cid":"UgjfmS9-agtZ6XgCoAEC","text":"1:33:45 - 1:33:59 legendary.","time":"5 years ago","author":"s643","channel":"UC7igYbPWpz7lHUT_Z5DBHaw","votes":"14","photo":"https:\/\/yt3.ggpht.com\/ytc\/AKedOLRPQQhrer6KPyPY5W2horNQdmau1locth_7zw=s176-c-k-c0x00ffffff-no-rj","heart":false},{"id_val":"bmJqPnV3Jrw","cid":"UgztvDll-4-3OU1eDFJ4AaABAg","text":"10:58 Damn. That's good.","time":"1 year ago","author":"Dheweyzz","channel":"UCdvvXWI8FYAGjayFkh5HEXA","votes":"9","photo":"https:\/\/yt3.ggpht.com\/nc5z72OB3XQUzWs88E9F7RlGT0-2bZM_VF9ssqW03x6tayOM2w5JwRE_YH2sBm0Rrwo5NopTjA=s176-c-k-c0x00ffffff-no-rj","heart":false},{"id_val":"bmJqPnV3Jrw","cid":"UghTOrYslHaX0ngCoAEC","text":"2:04:00 that chiming noise in the track from an iphone, while i was actually getting text messages using that same chime = mind fuck of epic proportions !!!","time":"5 years ago","author":"DJ Telso","channel":"UCtyLC1QdAOCVwU7jg-NigrQ","votes":"1","photo":"https:\/\/yt3.ggpht.com\/ytc\/AKedOLSeGE0z4sqgD0nQ__Husz7Caq-A3YDr_5HaFxpXqw=s176-c-k-c0x00ffffff-no-rj","heart":false},{"id_val":"bmJqPnV3Jrw","cid":"UghgjcRqCusBFngCoAEC","text":"Track Id a 1:05:00 that shit is insane! it literaly divides this great set in 2, wow","time":"5 years ago","author":"Gero Arrieta","channel":"UCOKCigMe3xJSvI-nu7oIWLQ","votes":"0","photo":"https:\/\/yt3.ggpht.com\/ytc\/AKedOLSUfnUr65YxKxgs_PEMewCiL3iIWYA9GkMw8HXL=s176-c-k-c0x00ffffff-no-rj","heart":false},{"id_val":"bmJqPnV3Jrw","cid":"UgiQ-1XVO1HjtngCoAEC.8IWkHdT0b1C8NaGa9ul8Su","text":"Track ID?","time":"4 years ago","author":"Attila Crazy","channel":"UCINyaD8jPK9Kl4IyGL4YmcQ","votes":"0","photo":"https:\/\/yt3.ggpht.com\/ytc\/AKedOLQyjhdGVXW7QCaNkSDFZUv1ZLbcsYt1Lh601hto4g=s176-c-k-c0x00ffffff-no-rj","heart":false},{"id_val":"bmJqPnV3Jrw","cid":"UgxFgH1hbxqmRvel13F4AaABAg","text":"58:00 is when we start to lift off folks","time":"8 days ago","author":"Matt Barratt","channel":"UCflfagLtaPPXDHoYPjXmuaQ","votes":"0","photo":"https:\/\/yt3.ggpht.com\/ytc\/AKedOLSGA7jlLXKrGX8ddghBcJyT816_pE90nR5c8Q=s176-c-k-c0x00ffffff-no-rj","heart":false},{"id_val":"bmJqPnV3Jrw","cid":"Ugg2OXiU10Gy6HgCoAEC","text":"01:11:00 [Rosper & Aplusplus - Bombshell] the best track!","time":"5 years ago","author":"I v a n F e g a r t","channel":"UCMsyLXjNLtM2EUcMnBj1cnA","votes":"10","photo":"https:\/\/yt3.ggpht.com\/ytc\/AKedOLTXbncrfDOj_tPNMCPpYh6YGLq_-A6DIE1cNQ=s176-c-k-c0x00ffffff-no-rj","heart":false},{"id_val":"bmJqPnV3Jrw","cid":"UgiKJGXM7YkdyngCoAEC","text":"1:25:43 Dubfire rules","time":"5 years ago","author":"Gorras Importadas","channel":"UC56o8CZgx308lzVenYU5waw","votes":"0","photo":"https:\/\/yt3.ggpht.com\/ytc\/AKedOLSvsvqHmOYW9c6Ol0sIaVZLAFbZiGg1tvVndQ=s176-c-k-c0x00ffffff-no-rj","heart":false},{"id_val":"bmJqPnV3Jrw","cid":"UgiOU3zgBq-A4XgCoAEC","text":"1:01:00 BOOOOOOOOOOOOOOOOOM!!!!","time":"5 years ago","author":"LeanEmmanuel","channel":"UCZzpsWDrfy-L_094DIpaT5g","votes":"2","photo":"https:\/\/yt3.ggpht.com\/ytc\/AKedOLSoSq7NMmwQJoNmd9ks0PlUf8-MjLYZoe_kEAUR=s176-c-k-c0x00ffffff-no-rj","heart":false},{"id_val":"bmJqPnV3Jrw","cid":"UggLlTJqtBbrFngCoAEC","text":"1:05:00 Raul Facio - Infinite (Original Mix)","time":"5 years ago","author":"MarlonTwist","channel":"UCEBiDdvCrAYHYb3ZagVtDHg","votes":"19","photo":"https:\/\/yt3.ggpht.com\/ytc\/AKedOLRRmhRJrYlvG-D8csP12vC-iHKEoaoMkdQTpUocXg=s176-c-k-c0x00ffffff-no-rj","heart":false},{"id_val":"bmJqPnV3Jrw","cid":"UghwaetZjqd5ZHgCoAEC","text":"1:57:00, unreleased remix of raumakustik - raider? omg that song is straight fire and the room goes cray\nthis is a question btw, if anybody knows this song or info about it release date plssss let me know","time":"5 years ago","author":"C\u00e9dric De Smet","channel":"UCWIXinQ8Ax4qaJHobLRAnvQ","votes":"1","photo":"https:\/\/yt3.ggpht.com\/ytc\/AKedOLTAL6wFTg4Cc1zd88BUM0uubHDYStJkN-Kuxw=s176-c-k-c0x00ffffff-no-rj","heart":false},{"id_val":"bmJqPnV3Jrw","cid":"UghEUfWkkY2xm3gCoAEC","text":"1:18:00 The Junkies - Living And Giving (Original Mix) [SCI-TEC]","time":"5 years ago","author":"Solomon Grundy","channel":"UCxHlPhiLr9YVDb1C18-SKmQ","votes":"4","photo":"https:\/\/yt3.ggpht.com\/ytc\/AKedOLTHTD0NgZXoK_HZV1crmPDW0MNhvJXdV9uF1yPz=s176-c-k-c0x00ffffff-no-rj","heart":false},{"id_val":"bmJqPnV3Jrw","cid":"UghcD5n_kBX-AHgCoAEC","text":"Track ID 54:00 - 56:00 please? What a set! \ud83d\udc4d\ud83c\udffc","time":"5 years ago","author":"Gemini","channel":"UCRo5iMB645WBTFc-JehvM6Q","votes":"4","photo":"https:\/\/yt3.ggpht.com\/RNUoSz3hqkaI-Y-kFM5zDo4sIHcXi03sfa9H50T3RNGtSEI55QtgmjFjlmXSLpAHBLCVaJjp=s176-c-k-c0x00ffffff-no-rj","heart":false},{"id_val":"bmJqPnV3Jrw","cid":"UgyNQhL7uqYlCjkGjJF4AaABAg","text":"1:35:00 <3","time":"2 years ago","author":"Ankit Sharma","channel":"UCvo2PbELycwiwcplIeK7P0A","votes":"0","photo":"https:\/\/yt3.ggpht.com\/ytc\/AKedOLTpiEItEpd2nE0pefBvByEvWmi4rTRVhRcq9TsfGg=s176-c-k-c0x00ffffff-no-rj","heart":false},{"id_val":"bmJqPnV3Jrw","cid":"Ugjw2bKXVE2k3HgCoAEC","text":"1:10:00 A++ & Rosper - Bombshell (Original Mix) [Sci+Tec] :)","time":"5 years ago","author":"Consumed Music","channel":"UCe2QBJqFlUX_Kpb6xNAAo8g","votes":"2","photo":"https:\/\/yt3.ggpht.com\/ytc\/AKedOLQ9gXiS5CNhPzLDPo9S-hGhCXOxn-sRZ2rlmuv9nto=s176-c-k-c0x00ffffff-no-rj","heart":false},{"id_val":"bmJqPnV3Jrw","cid":"UgiIsoAnBP3BKHgCoAEC","text":"1:05:30 A cowboy emerges from hell","time":"5 years ago","author":"Dino D'ambrosio","channel":"UCcHiqQg30ktMKtgYtEgtIPQ","votes":"0","photo":"https:\/\/yt3.ggpht.com\/ytc\/AKedOLSCAOUBEQ0Nfvan6ftLTbAJkCmFAyUGyqISGTDwZGk=s176-c-k-c0x00ffffff-no-rj","heart":false},{"id_val":"bmJqPnV3Jrw","cid":"UgjVhAkmyPSKi3gCoAEC.8ASm2Y9wrWO9FtJRXuBiZy","text":"Tracktor and Ableton link","time":"1 year ago","author":"ArtOfficial Music","channel":"UCHKQAylwHZMdhWDGxa9q7Cg","votes":"1","photo":"https:\/\/yt3.ggpht.com\/n-SzItHEkLhJ8VNX7n3cFaUPWGkVyyLDYEjRKL2CU7up2PkFU0Vz-O-aAS8fJzD5pYuGd47XtQ=s176-c-k-c0x00ffffff-no-rj","heart":false},{"id_val":"bmJqPnV3Jrw","cid":"UgxCUoeEawEMLZtFGF94AaABAg","text":"52:15 <3","time":"2 years ago","author":"Ankit Sharma","channel":"UCvo2PbELycwiwcplIeK7P0A","votes":"0","photo":"https:\/\/yt3.ggpht.com\/ytc\/AKedOLTpiEItEpd2nE0pefBvByEvWmi4rTRVhRcq9TsfGg=s176-c-k-c0x00ffffff-no-rj","heart":false},{"id_val":"bmJqPnV3Jrw","cid":"UgxWhgtcMHXekjx1kKN4AaABAg","text":"17:50 <3","time":"2 years ago","author":"Ankit Sharma","channel":"UCvo2PbELycwiwcplIeK7P0A","votes":"0","photo":"https:\/\/yt3.ggpht.com\/ytc\/AKedOLTpiEItEpd2nE0pefBvByEvWmi4rTRVhRcq9TsfGg=s176-c-k-c0x00ffffff-no-rj","heart":false},{"id_val":"bmJqPnV3Jrw","cid":"Ugxfi3AqfpHKcsV5y0h4AaABAg","text":"1:37:00 Good song","time":"1 year ago","author":"David TodasMias19","channel":"UC37ZEgDH6Kw-5Ltt52y_F2g","votes":"0","photo":"https:\/\/yt3.ggpht.com\/ytc\/AKedOLS0Todtt_G5pWilK8cJ-QRyI2ZgGfTbSbfUUA=s176-c-k-c0x00ffffff-no-rj","heart":false},{"id_val":"bmJqPnV3Jrw","cid":"UggQ8LGD9Ai0pHgCoAEC","text":"Track 1:05:30  Raul Facio - Infinite ( SCI+TEC)","time":"5 years ago","author":"The Strangers","channel":"UCsXMzv_UJQcVCDPSeKD9Tag","votes":"3","photo":"https:\/\/yt3.ggpht.com\/ytc\/AKedOLRF4T4GWsBdI6tnLseT6OiPMufazQIhxftAOrqc=s176-c-k-c0x00ffffff-no-rj","heart":false},{"id_val":"bmJqPnV3Jrw","cid":"UggrXRgDXeqgGHgCoAEC","text":"1:55:00 Ctrls-displacer(sleeparchive version 1)","time":"4 years ago","author":"Jambowstel !!","channel":"UCQJ2v7fqIwM6nbzmkSABOoQ","votes":"1","photo":"https:\/\/yt3.ggpht.com\/ytc\/AKedOLTwYU1XItr3JAuMBvlf1GUeoyk_M3mdHaUAow=s176-c-k-c0x00ffffff-no-rj","heart":false},{"id_val":"bmJqPnV3Jrw","cid":"Ugy6GtY32P54gijXPXp4AaABAg","text":"1:02:30 Please does anyone know what that track is called?","time":"11 months ago","author":"denis calderon","channel":"UCx5Wy0Yg7E_bVjUMs3x2zZQ","votes":"0","photo":"https:\/\/yt3.ggpht.com\/ytc\/AKedOLQ1EnITUYuC8AcR6NSsz9dsfUAiC2KBnyz53sNZO7w=s176-c-k-c0x00ffffff-no-rj","heart":false},{"id_val":"bmJqPnV3Jrw","cid":"UgjGMrgBRPzQIHgCoAEC","text":"1:45:38 sooo good, ID pls","time":"5 years ago","author":"Un3X1sT","channel":"UCVGjOXESNdWjubwyQYxElzA","votes":"0","photo":"https:\/\/yt3.ggpht.com\/ytc\/AKedOLQtg6pbCPMq-gf688uHPQ4FNMCbHN-fSrMPug=s176-c-k-c0x00ffffff-no-rj","heart":false},{"id_val":"bmJqPnV3Jrw","cid":"UghVh6W8jUO9VngCoAEC","text":"1:42:37      TRACK OF VICTORY ..... a give a good vibes and LOVE for track ID PLEASE <3","time":"5 years ago","author":"MATEOQWE1","channel":"UC2r7VENqJSmQCu84yjdu_LA","votes":"0","photo":"https:\/\/yt3.ggpht.com\/ytc\/AKedOLTnV0lCj1HPJzj5dvu5YOzJtMA2lHW22Cs4Nw=s176-c-k-c0x00ffffff-no-rj","heart":false},{"id_val":"bmJqPnV3Jrw","cid":"UgwYkzP2gcjCQ1rFDhl4AaABAg","text":"55:37 my fucking god","time":"11 months ago","author":"Ikariotiko Stigma","channel":"UCt4nwlkOzKQgL9zRH3Yoi6Q","votes":"0","photo":"https:\/\/yt3.ggpht.com\/ytc\/AKedOLSgS42HR3XzQMzPpOKuJZMDgX9Cu-orGTTAyDJt=s176-c-k-c0x00ffffff-no-rj","heart":false},{"id_val":"bmJqPnV3Jrw","cid":"Ugi0naBdcbBFAHgCoAEC","text":"Track at 1 hour 39 minute mark ?????????? BOMB!","time":"5 years ago","author":"jamiesomersuk","channel":"UCXcGxSa8znWn4UKpCfp_zew","votes":"1","photo":"https:\/\/yt3.ggpht.com\/ytc\/AKedOLTdx8h2mDmecX4kBIqe6nr2aCHpTHOHxaY8taCH=s176-c-k-c0x00ffffff-no-rj","heart":false},{"id_val":"bmJqPnV3Jrw","cid":"UgjkIJ73kC83mXgCoAEC","text":"Track @ 1h22 with the acid and percussion?! :D","time":"5 years ago","author":"pollewops89","channel":"UCQTSy9FTBQlcmWqzybG2ZCQ","votes":"5","photo":"https:\/\/yt3.ggpht.com\/ytc\/AKedOLRmDqmRAfCf5PRegpjb6rHOSErW7o_RcbNMHA=s176-c-k-c0x00ffffff-no-rj","heart":false},{"id_val":"bmJqPnV3Jrw","cid":"UgzHN2Icv0hW_MfjDg14AaABAg","text":"1:22:00 Acid sounds. Track??? Massive","time":"4 years ago","author":"Swar Raveshia","channel":"UCkBuyKhUCMgqDIQx7v-scNg","votes":"0","photo":"https:\/\/yt3.ggpht.com\/ytc\/AKedOLT2-VRT99E_V6tKS-Qvo8skHKRYuBgwRntxU2a0SA=s176-c-k-c0x00ffffff-no-rj","heart":false},{"id_val":"bmJqPnV3Jrw","cid":"UggYNb2pwHDTCHgCoAEC","text":"Track ID 52:00 to 58:00 , driving me nuts","time":"5 years ago","author":"Artefact","channel":"UCjegFNB_2nws6TV8wsi61mA","votes":"22","photo":"https:\/\/yt3.ggpht.com\/ytc\/AKedOLTB2NK6_v86QL2w_lul8VG8X5IPAM1tO_FSkM-l=s176-c-k-c0x00ffffff-no-rj","heart":false},{"id_val":"bmJqPnV3Jrw","cid":"UgxYYMM54t8g_52Vi4F4AaABAg","text":"33:30 Ryan James Ford - Arco Pitcairn","time":"1 year ago","author":"Kostas Rudy","channel":"UCImGBzmfaO_mKBisuSjXfSg","votes":"1","photo":"https:\/\/yt3.ggpht.com\/ytc\/AKedOLQooFXLaEzAKBn44ZXdgKNutRNVtwbZHHuvaA=s176-c-k-c0x00ffffff-no-rj","heart":false},{"id_val":"bmJqPnV3Jrw","cid":"UghlMsl_0qaYEHgCoAEC","text":"41:00 Tale Of Us - Silent Space","time":"4 years ago","author":"Juan Endrizzi","channel":"UC8yHbZqVgA-u_Y0hA8udYwQ","votes":"0","photo":"https:\/\/yt3.ggpht.com\/ytc\/AKedOLRMgAtBQ_oK-5JTDh_OSxZL0UvQzEQYsfkgw7arjA=s176-c-k-c0x00ffffff-no-rj","heart":false},{"id_val":"bmJqPnV3Jrw","cid":"Ugis6RddmpsLMngCoAEC","text":"Track ID for 1:21:15?","time":"4 years ago (edited)","author":"Cy","channel":"UCnmIZQyVv6NbNd-osdf8hxw","votes":"0","photo":"https:\/\/yt3.ggpht.com\/ytc\/AKedOLRbXvjW_EEznDKB8nFDT-A0Lg_HsDEp7vpn1g=s176-c-k-c0x00ffffff-no-rj","heart":false},{"id_val":"bmJqPnV3Jrw","cid":"Ugib-rpyQPkg-HgCoAEC","text":"1:40:00 please give this goddamn track;s name!!!!, going insane over this tune!!","time":"5 years ago","author":"Fuck Libtards","channel":"UCCPqcdLeX3LBp_hmQ7mbIRA","votes":"2","photo":"https:\/\/yt3.ggpht.com\/ytc\/AKedOLQqosWUoH8VmEqeXJxebk1kpUArXzc3KRNRHQ=s176-c-k-c0x00ffffff-no-rj","heart":false},{"id_val":"bmJqPnV3Jrw","cid":"UgxiazY9fmPL8rK6JGV4AaABAg","text":"12:24 the guy on the left starts his attack on brunette girl while her friend stay dancing alone for a few seconds. Bald guy appears on 12:42 and tries to complete the dancing scene but it doesn't works  :(","time":"3 years ago","author":"Alejandro Candon","channel":"UCSAG3Sso-ftUdG2wg6R6i_A","votes":"1","photo":"https:\/\/yt3.ggpht.com\/ytc\/AKedOLSqWcZgbFdy9blgSPlq5G74VDTtE44NZMnBfw=s176-c-k-c0x00ffffff-no-rj","heart":false},{"id_val":"bmJqPnV3Jrw","cid":"UgxznG1KBMg9dVFcHyl4AaABAg","text":"1:05:35\ud83e\udd23\ud83e\udd23\ud83e\udd23\ud83e\udd23","time":"3 years ago (edited)","author":"Heiner Cordero","channel":"UCO3KYaRSW7NRjzc9gDGLg0A","votes":"0","photo":"https:\/\/yt3.ggpht.com\/ytc\/AKedOLTAOpcpwSabl1w8PpgU2yqJXF5zxfsmuGB_e-5f=s176-c-k-c0x00ffffff-no-rj","heart":false},{"id_val":"bmJqPnV3Jrw","cid":"UggwKtXheEdcQHgCoAEC","text":"1:56 ? neeeeeeed it","time":"5 years ago","author":"LeGr\u00f6","channel":"UCjEWJV_wDSGOI6jHRDoyrEA","votes":"0","photo":"https:\/\/yt3.ggpht.com\/ytc\/AKedOLQbZoUIt7Aa9rwz9ZSgrxfrL2ZPvoFn4cQgXXdX=s176-c-k-c0x00ffffff-no-rj","heart":false},{"id_val":"bmJqPnV3Jrw","cid":"Ugjr-20WrD5533gCoAEC","text":"1:38:00 I BEG YOU!","time":"5 years ago","author":"Jakub Korzeniowski","channel":"UCnxCZOfM9KVo9S-j1ndreHg","votes":"1","photo":"https:\/\/yt3.ggpht.com\/ytc\/AKedOLSzczTxhyYdMRqx8iRrOuyiUKmnh6Pl9vgm_q16wWQ=s176-c-k-c0x00ffffff-no-rj","heart":false},{"id_val":"bmJqPnV3Jrw","cid":"Ugi3ew8XXYDkO3gCoAEC","text":"59:00 Paul Strive & Zenbi - Wanna Tell You BOMB","time":"5 years ago","author":"pisti19brksd","channel":"UCq55PZ8wRAGSMrpxXG7jplg","votes":"1","photo":"https:\/\/yt3.ggpht.com\/ytc\/AKedOLTAJBUO0uydB6Voe-8oH26QyHU1wuqwjjA-bg=s176-c-k-c0x00ffffff-no-rj","heart":false},{"id_val":"bmJqPnV3Jrw","cid":"UgxwWCUfgZbdcF-EgP94AaABAg","text":"Track ID 01:12:00??? \ud83d\ude0d","time":"1 year ago","author":"Daniel","channel":"UCPDU1lOje11-xYuxlW4bg5A","votes":"0","photo":"https:\/\/yt3.ggpht.com\/ytc\/AKedOLQKAsw6oSvJocyQczkeyh2yO1sLtYqnVIFVKl_Jbw=s176-c-k-c0x00ffffff-no-rj","heart":false},{"id_val":"bmJqPnV3Jrw","cid":"Ugg4iQPPQP3uY3gCoAEC","text":"1:32:14","time":"5 years ago","author":"Flow gvng","channel":"UC4UtTg-tgo-96jRQvptcwjA","votes":"1","photo":"https:\/\/yt3.ggpht.com\/ytc\/AKedOLSN9n8VhiSCrCT-VgwXlo-AGGozRCqOIxmKbIcSzA=s176-c-k-c0x00ffffff-no-rj","heart":false},{"id_val":"bmJqPnV3Jrw","cid":"Ughh35IRxiUa-ngCoAEC","text":"58:00 Track ID PLEASE!","time":"5 years ago","author":"sofia martinez rodriguez","channel":"UCYYU61rQgka4hYugD68TggA","votes":"0","photo":"https:\/\/yt3.ggpht.com\/ytc\/AKedOLRj5jXwD95-TJJGsn7FB_i79XP4hQziN4JVm10I4QI=s176-c-k-c0x00ffffff-no-rj","heart":false},{"id_val":"bmJqPnV3Jrw","cid":"UgxAL5-pXcY6hAJOmXt4AaABAg","text":"1:03:00,1:10:40","time":"1 year ago (edited)","author":"markus seib","channel":"UCbcm4Hxk__hw9i9eeSWqGMQ","votes":"0","photo":"https:\/\/yt3.ggpht.com\/ytc\/AKedOLSYdWjZZOyf0zZxCv0YXFNu4MdLE0yI-5Fp5F_W=s176-c-k-c0x00ffffff-no-rj","heart":false},{"id_val":"bmJqPnV3Jrw","cid":"UgwY9Mmb6PIiP3-pt5l4AaABAg","text":"7:30 que hace en ese momento ? por lo visto absolutamente nada , simulando mover perillas ... que alguien me explique.","time":"4 years ago","author":"Sirist10","channel":"UCulG-u9Q5aoeonpJbdeLgLg","votes":"0","photo":"https:\/\/yt3.ggpht.com\/ytc\/AKedOLSMYWOaHUOeIMFOybkRWmyDaKzC3evKL2k9Qyw=s176-c-k-c0x00ffffff-no-rj","heart":false},{"id_val":"bmJqPnV3Jrw","cid":"Ugg1vQ7RjIpNA3gCoAEC","text":"1:34:35","time":"5 years ago","author":"Dylan Mckay","channel":"UCyB_RGfmOfrcseVOiJKoBPg","votes":"1","photo":"https:\/\/yt3.ggpht.com\/ytc\/AKedOLTEiFaX6u66Knufh_UkZm7c5CGcNdacvi2TUg=s176-c-k-c0x00ffffff-no-rj","heart":false},{"id_val":"bmJqPnV3Jrw","cid":"UgiiRrkeFtWRM3gCoAEC","text":"1:05:30 track ?????Boom","time":"5 years ago","author":"Joseph","channel":"UCxvIW_7CVL50JSj22A_ghTw","votes":"1","photo":"https:\/\/yt3.ggpht.com\/ytc\/AKedOLTJXwbAdbly6-0uSJs-8zJr21k3wtm2ZqIfWMqw=s176-c-k-c0x00ffffff-no-rj","heart":false},{"id_val":"bmJqPnV3Jrw","cid":"Ugh6YVcAbcmUvHgCoAEC","text":"2:00:00 track please?","time":"5 years ago","author":"GEORGE G","channel":"UCfTWuUneB9AqYNnHTZKJHtw","votes":"8","photo":"https:\/\/yt3.ggpht.com\/ytc\/AKedOLQi6ls-Jw0RjTLSLRfbRztkac8FY3WQlSnFD_fH=s176-c-k-c0x00ffffff-no-rj","heart":false},{"id_val":"bmJqPnV3Jrw","cid":"Ugwe0MCBavxbQrgjvIl4AaABAg","text":"1:30:00","time":"1 year ago","author":"Luc\u00eda Pucheta","channel":"UCXRfQk1Q2vx8vv8mTmqac4g","votes":"0","photo":"https:\/\/yt3.ggpht.com\/ytc\/AKedOLRX8_BneutoaU1wtLw-ylpZoBtA4mIihSrr6w=s176-c-k-c0x00ffffff-no-rj","heart":false},{"id_val":"bmJqPnV3Jrw","cid":"UgiDY9fiGCUr-HgCoAEC","text":"1:06 track id please ?","time":"5 years ago","author":"Silver Portugov","channel":"UCywR6rLw8utFfHoYUJi0rHg","votes":"0","photo":"https:\/\/yt3.ggpht.com\/ytc\/AKedOLR-dkEzuJldbn-gOffTII-tOk5M61miSALD8HlSBw=s176-c-k-c0x00ffffff-no-rj","heart":false},{"id_val":"bmJqPnV3Jrw","cid":"UghftQ2SsvieoHgCoAEC","text":"Track at 1h:38m ??","time":"5 years ago","author":"Andrea Tripodi","channel":"UCVEOxJ_rVma1zJpUdP3kcFA","votes":"2","photo":"https:\/\/yt3.ggpht.com\/ytc\/AKedOLQbrGrggchLXdPCnka07V2lM0EAkHl24VVAP9NN=s176-c-k-c0x00ffffff-no-rj","heart":false},{"id_val":"bmJqPnV3Jrw","cid":"UgjYlywCH1vxj3gCoAEC","text":"35:00 song please!!!!!!","time":"5 years ago","author":"Guro Gulikashvili","channel":"UCRD17QZWzrGMTfVeLMkFVjg","votes":"4","photo":"https:\/\/yt3.ggpht.com\/ytc\/AKedOLQSG62BjTZHRIytLJG9pq6f89ZX62cylD5vNt6d=s176-c-k-c0x00ffffff-no-rj","heart":false},{"id_val":"bmJqPnV3Jrw","cid":"UgirpsbrO9iOdHgCoAEC","text":"37:00 Ryan James Ford - Arco Pitcairn","time":"5 years ago","author":"Bal\u00e1zs P\u00e1lya","channel":"UCDqoYxk40-5fG0dUlt7TdXg","votes":"4","photo":"https:\/\/yt3.ggpht.com\/ytc\/AKedOLTvWz8MZ0Ff87L90rwRu90GXPBugkWkepoMhlRh3w=s176-c-k-c0x00ffffff-no-rj","heart":false},{"id_val":"bmJqPnV3Jrw","cid":"UgjqnmslJuJstXgCoAEC","text":"53:00 track id?","time":"5 years ago","author":"Giancarlo Pelosi","channel":"UCRwWTlqLxceGc2ZsM1_teQg","votes":"1","photo":"https:\/\/yt3.ggpht.com\/ytc\/AKedOLSkXIcJAiJ2_rculZ5pP0w5y8O4d8hRTsQHayTVAQ=s176-c-k-c0x00ffffff-no-rj","heart":false},{"id_val":"bmJqPnV3Jrw","cid":"UgiiRWUt2sPwFXgCoAEC","text":"Track ID @ 1:05:30 ?","time":"5 years ago","author":"kikzor","channel":"UC3BvC_4j8-GejqfV6CpcvBA","votes":"0","photo":"https:\/\/yt3.ggpht.com\/ytc\/AKedOLS5f81FXnYS-KnfobXCeSFM9yp-ni2tTIgv3w=s176-c-k-c0x00ffffff-no-rj","heart":false},{"id_val":"bmJqPnV3Jrw","cid":"UggtwIlD3UgUvXgCoAEC","text":"18:20 track id?","time":"5 years ago","author":"Andrew Sthefans","channel":"UCRH_mHD46lEmgzqTLan_waw","votes":"0","photo":"https:\/\/yt3.ggpht.com\/ytc\/AKedOLQIa2hBEbEY7VbOIqRJodPLL4nYBfqzoOc3GYrp=s176-c-k-c0x00ffffff-no-rj","heart":false},{"id_val":"bmJqPnV3Jrw","cid":"UgiiTcvFveWX1ngCoAEC","text":"1:29:00 track id anyone?! danke","time":"5 years ago","author":"JallE","channel":"UCcCOoyM52ZOMeqIrPzxc7aQ","votes":"4","photo":"https:\/\/yt3.ggpht.com\/ytc\/AKedOLTqawvwuSfZsl3uC5bO_sWJOmzurIdAb-6NYvyh=s176-c-k-c0x00ffffff-no-rj","heart":false},{"id_val":"bmJqPnV3Jrw","cid":"UghC-iFYEbQnUXgCoAEC","text":"2:04:00 track ?","time":"5 years ago","author":"bardhok zymberi","channel":"UC0MSV38ZskFyZxO6zzzZZRQ","votes":"0","photo":"https:\/\/yt3.ggpht.com\/ytc\/AKedOLSyFIYtn0YdOslYAYn7o0OT7dlCGZQ-4_NHTDT9=s176-c-k-c0x00ffffff-no-rj","heart":false},{"id_val":"bmJqPnV3Jrw","cid":"Ugxd5TO5tHxb4SlxqP94AaABAg","text":"2:13:36 track id???","time":"1 year ago (edited)","author":"Luc\u00eda Pucheta","channel":"UCXRfQk1Q2vx8vv8mTmqac4g","votes":"0","photo":"https:\/\/yt3.ggpht.com\/ytc\/AKedOLRX8_BneutoaU1wtLw-ylpZoBtA4mIihSrr6w=s176-c-k-c0x00ffffff-no-rj","heart":false},{"id_val":"bmJqPnV3Jrw","cid":"UggMEXs3DDjh4HgCoAEC","text":"58:18 track ID?","time":"5 years ago","author":"Raffaele Leone","channel":"UCsNARJbfJXrdpI9cyal4HVw","votes":"4","photo":"https:\/\/yt3.ggpht.com\/ytc\/AKedOLSDj7m7nhzCQiatvlGX8oZTOHoj8UBDTH7Dc3olMw=s176-c-k-c0x00ffffff-no-rj","heart":false},{"id_val":"bmJqPnV3Jrw","cid":"Ughy3f0uUtpkK3gCoAEC","text":"1:05:35 min track id anyone?","time":"5 years ago","author":"Gaming & Tech","channel":"UCHi4SV_qbwVpUl4GkcOcCeQ","votes":"0","photo":"https:\/\/yt3.ggpht.com\/pOxpZsgLXE9hdf0S9LINE20xHYA0DhDkcMU5UzEAmrWWBf2YzCF_4V_KvdWi5gDSeFqIMzECwg=s176-c-k-c0x00ffffff-no-rj","heart":false},{"id_val":"bmJqPnV3Jrw","cid":"UgwdOpv-re-JfUQFNMR4AaABAg","text":"1:49:00 track name pls","time":"8 months ago","author":"\u0410\u043b\u0435\u043a\u0441\u0430\u043d\u0434\u0440 \u041c\u0435\u043b\u044c\u043d\u0438\u043a","channel":"UCgFSmcst2IZMmdRKX7X9niw","votes":"0","photo":"https:\/\/yt3.ggpht.com\/ytc\/AKedOLR8fqY5K8LWPPBUd24G64K9KeoL3iiQO7XaPA=s176-c-k-c0x00ffffff-no-rj","heart":false},{"id_val":"bmJqPnV3Jrw","cid":"Ugglwf9XMB6ZV3gCoAEC","text":"Track at 1:20:00??","time":"5 years ago","author":"David Prigg","channel":"UCsEEKHCc0Jgx_Ch6Ixha6BQ","votes":"0","photo":"https:\/\/yt3.ggpht.com\/ytc\/AKedOLSPy8RVn9pbQgzGelIj-glyI579j6Z4IIw_cA=s176-c-k-c0x00ffffff-no-rj","heart":false},{"id_val":"bmJqPnV3Jrw","cid":"UgwKfdkX81dnqksJmMJ4AaABAg","text":"40:45","time":"3 years ago","author":"MOHAYMEN Music","channel":"UCl66OXTKd-bbFtW22KbdZtA","votes":"0","photo":"https:\/\/yt3.ggpht.com\/ytc\/AKedOLQjkBAd8PpEQWRCV7p3u8ND7rqfcwiuJpWB8Wk8=s176-c-k-c0x00ffffff-no-rj","heart":false},{"id_val":"bmJqPnV3Jrw","cid":"UggNJ_xv81LWwngCoAEC","text":"1:18:00 track id????","time":"5 years ago","author":"Kais Essaied","channel":"UCCHoQilNa8Bc4oLzXWPBA7A","votes":"1","photo":"https:\/\/yt3.ggpht.com\/ytc\/AKedOLRNyhxakeHfDYkbSDG2cnvw81Vh2xOjR27TXLsX6Q=s176-c-k-c0x00ffffff-no-rj","heart":false},{"id_val":"bmJqPnV3Jrw","cid":"UghfmdOPcAiZa3gCoAEC","text":"Track Id @ 1:05:30 ?","time":"5 years ago","author":"vivamalta","channel":"UCIDbHB2BDzjXjCwtm6LjoGg","votes":"1","photo":"https:\/\/yt3.ggpht.com\/ytc\/AKedOLRi8Ky_cLKASz7V-VZFJ3ws9_lKeTDRvLiDcoMJ=s176-c-k-c0x00ffffff-no-rj","heart":false},{"id_val":"bmJqPnV3Jrw","cid":"UgjEIhWCTi9mtngCoAEC","text":"1:30:00 please!!","time":"5 years ago","author":"Lotreanu Adrian","channel":"UCCY9NOj82QneSQlauO4OTNw","votes":"3","photo":"https:\/\/yt3.ggpht.com\/ytc\/AKedOLSYgz1smVeyhw7zGRsN-EQ4iMwCN_Vg3Svkqhm_=s176-c-k-c0x00ffffff-no-rj","heart":false},{"id_val":"bmJqPnV3Jrw","cid":"UghIHXIcvys2MXgCoAEC","text":"1:04:30 track id","time":"5 years ago","author":"Alvaro Lou","channel":"UCM21LPamhBHv-6MFuUA0-0w","votes":"1","photo":"https:\/\/yt3.ggpht.com\/ytc\/AKedOLTp9mELT3of2qTmH1nyWJT_jsKL8ri_y3rbu5AXHuo=s176-c-k-c0x00ffffff-no-rj","heart":false},{"id_val":"bmJqPnV3Jrw","cid":"UgiZbJJGMvk_tXgCoAEC","text":"1:55:00 track id?","time":"5 years ago","author":"Felipe Labouriau","channel":"UCK8EV5kqoektICE9X5D1VDw","votes":"3","photo":"https:\/\/yt3.ggpht.com\/ytc\/AKedOLT06pbl4EJvDqvJMcWWXHlqW9h24u_d-LSGDOnD=s176-c-k-c0x00ffffff-no-rj","heart":false},{"id_val":"bmJqPnV3Jrw","cid":"Ughsz37k3dCv9HgCoAEC","text":"1:08:00 track please","time":"5 years ago","author":"le.qru","channel":"UCNJA3yC-FRTvnoMhdscDQKA","votes":"0","photo":"https:\/\/yt3.ggpht.com\/ytc\/AKedOLQCA2zQ8XIpt0SfLnx_KTLu8znAaSXTxdc5VjFN=s176-c-k-c0x00ffffff-no-rj","heart":false},{"id_val":"bmJqPnV3Jrw","cid":"UgwmSf7d-dAFQA2ODX94AaABAg","text":"52:30","time":"11 months ago","author":"Ikariotiko Stigma","channel":"UCt4nwlkOzKQgL9zRH3Yoi6Q","votes":"0","photo":"https:\/\/yt3.ggpht.com\/ytc\/AKedOLSgS42HR3XzQMzPpOKuJZMDgX9Cu-orGTTAyDJt=s176-c-k-c0x00ffffff-no-rj","heart":false},{"id_val":"bmJqPnV3Jrw","cid":"Ugz5j4ZYDaTWVAgELOJ4AaABAg","text":"Track first 20 minutes ???\nHelp \ud83d\udc50\ud83d\udc50\ud83d\udc50","time":"3 years ago","author":"Christian Dorra","channel":"UCcp5Iac7F6PO_65zzjwKXfg","votes":"0","photo":"https:\/\/yt3.ggpht.com\/-N1OE6RA_TlUNbAJ0atsMKOYsR6S9buDE5qxTdRkDqxzevRL4T0kRDr_CsqcyI164xpH-3DL=s176-c-k-c0x00ffffff-no-rj","heart":false},{"id_val":"bmJqPnV3Jrw","cid":"Ugg7HNOTk3kUlXgCoAEC","text":"2:10:30 track pls","time":"5 years ago","author":"Franti\u0161ek Piekar","channel":"UCJJCJjfP-oLsxrEaWdg-csg","votes":"0","photo":"https:\/\/yt3.ggpht.com\/ytc\/AKedOLSG8OF-3pcwyzGhDIX0jJ0pvZYrztbASfxfLnZS=s176-c-k-c0x00ffffff-no-rj","heart":false},{"id_val":"bmJqPnV3Jrw","cid":"UgxPSnBOzQNo_OgII7h4AaABAg","text":"12:35 Lara Croft i love you","time":"3 years ago","author":"Kaymak K","channel":"UCBBNWAEFXsl1zKEloKAl3Sw","votes":"0","photo":"https:\/\/yt3.ggpht.com\/ytc\/AKedOLQCnlmMPvKCADoZw7yWyBxNlSx22FS6ZtfnEQ=s176-c-k-c0x00ffffff-no-rj","heart":false},{"id_val":"bmJqPnV3Jrw","cid":"UgwvpSP3K3I0mXfosy14AaABAg","text":"1:14:00 please!","time":"3 years ago","author":"Manish","channel":"UCxitr2xJoCjIQW7AXCQYEqw","votes":"0","photo":"https:\/\/yt3.ggpht.com\/ytc\/AKedOLSftyAotB37iFXW4k8vbUgRe_L_yhVnkcKGawY2SQ=s176-c-k-c0x00ffffff-no-rj","heart":false},{"id_val":"bmJqPnV3Jrw","cid":"Ugg6N4mSlYOq53gCoAEC","text":"1:20!? Pleeeeease!","time":"5 years ago","author":"Ryan Collins","channel":"UCu_5Q33idc98GHPZ9HFlHgg","votes":"1","photo":"https:\/\/yt3.ggpht.com\/ytc\/AKedOLQI-10G7rs-fmtsMmscPkW2halNKYcfYQ4RxQ=s176-c-k-c0x00ffffff-no-rj","heart":false},{"id_val":"bmJqPnV3Jrw","cid":"UgiMsGAU9cd42XgCoAEC","text":"2:09:40 Staffan Linzatti - On who's behalf?","time":"5 years ago","author":"Damian Suarez","channel":"UCAlc5O7KWFszCHaW6Nc-u6A","votes":"1","photo":"https:\/\/yt3.ggpht.com\/ytc\/AKedOLTrxRkqzsRqlzThqsFAYnT3BmLj8b8v8YA08tJqyjE=s176-c-k-c0x00ffffff-no-rj","heart":false},{"id_val":"bmJqPnV3Jrw","cid":"UgiwuPYijessmXgCoAEC","text":"Track @55min plzzzzzzzzzzzzzzzz","time":"5 years ago","author":"Ait Bahajji Ali","channel":"UCHF-swidt9lMTGxpYn5BIHg","votes":"0","photo":"https:\/\/yt3.ggpht.com\/ytc\/AKedOLTZ0l_m_6O5hVBbYcOk0R6NG3rPJd2h6pl2SQ=s176-c-k-c0x00ffffff-no-rj","heart":false},{"id_val":"bmJqPnV3Jrw","cid":"Ugja2b6hASds-HgCoAEC","text":"1:10:00 song?","time":"5 years ago","author":"Bosh Gaming","channel":"UCwhuLe_XaiMGiKJszGEn91Q","votes":"0","photo":"https:\/\/yt3.ggpht.com\/ytc\/AKedOLQZPsLwBnhIRYncUDMgWqX1WedYm5RXOa_F9i9wmA=s176-c-k-c0x00ffffff-no-rj","heart":false},{"id_val":"bmJqPnV3Jrw","cid":"UgiwUrRV5Ljiu3gCoAEC","text":"2:18:00 anyone?","time":"5 years ago","author":"BLV","channel":"UCnNdnBPw2mxln5pT2x_deiA","votes":"0","photo":"https:\/\/yt3.ggpht.com\/ytc\/AKedOLRBTaxg7bPR5EYnONJg_bDsSZdvwx8tNoLgVPW3oUrwmyaRu2c28z8RkdAAtuw0=s176-c-k-c0x00ffffff-no-rj","heart":false},{"id_val":"bmJqPnV3Jrw","cid":"UgjUWJiLgA1TJ3gCoAEC","text":"2:05:02 id ?","time":"5 years ago","author":"darktower","channel":"UC-KvXTORRw1JY36IMQ76usw","votes":"0","photo":"https:\/\/yt3.ggpht.com\/ytc\/AKedOLQasmE6bT-SzoaosKsShqsxeVVMNUa5dUs6kjn1=s176-c-k-c0x00ffffff-no-rj","heart":false},{"id_val":"bmJqPnV3Jrw","cid":"UghehWr7hiq3lXgCoAEC","text":"1:25:00 ??","time":"5 years ago","author":"Logan Coste","channel":"UCKyw0_QNAf2HmpU3i87k_pQ","votes":"1","photo":"https:\/\/yt3.ggpht.com\/ytc\/AKedOLSxcVV3Ecf75z1F6-EWZJGEGRF-l5wVCClSUg=s176-c-k-c0x00ffffff-no-rj","heart":false},{"id_val":"bmJqPnV3Jrw","cid":"Ugg9ha0aH9S38HgCoAEC","text":"59:00 anyone??","time":"5 years ago","author":"belial","channel":"UCK41VSJmrMdMvPdfC3VRj4A","votes":"1","photo":"https:\/\/yt3.ggpht.com\/ytc\/AKedOLSWQ1iRMkMpsIgQjOsr4STLlH5LuyIkSCxr4Qo5xto=s176-c-k-c0x00ffffff-no-rj","heart":false},{"id_val":"bmJqPnV3Jrw","cid":"UgjFx3BDXlQk5XgCoAEC","text":"3:27 id?","time":"5 years ago","author":"panaphonics FSB","channel":"UCSSwAAp6zkjAWlMvSjkYzsw","votes":"0","photo":"https:\/\/yt3.ggpht.com\/ytc\/AKedOLSX-G3jZhhwYcdexqLixlC5xSEhlvKANrLXOXxY=s176-c-k-c0x00ffffff-no-rj","heart":false},{"id_val":"bmJqPnV3Jrw","cid":"UghHm47gxI7KzHgCoAEC","text":"1:33:50    \n\nMaksim Dark - Basserwiser","time":"5 years ago","author":"Koneser","channel":"UC3KKzXLt87q0nsywSApFVZw","votes":"6","photo":"https:\/\/yt3.ggpht.com\/ytc\/AKedOLTFD9OmU_bdngU6jc-Mlq8OyJbd_tmutDu9KZA=s176-c-k-c0x00ffffff-no-rj","heart":false},{"id_val":"bmJqPnV3Jrw","cid":"UgjU4df_M86ufXgCoAEC","text":"1:07 ish anyone. PEW PEW","time":"5 years ago","author":"kabamba","channel":"UCE8tWTIWb6YzwLwLVconBMg","votes":"1","photo":"https:\/\/yt3.ggpht.com\/ytc\/AKedOLTikDrBC7D76W0VO3MaCEdg6JR1auI4JniGeA=s176-c-k-c0x00ffffff-no-rj","heart":false},{"id_val":"bmJqPnV3Jrw","cid":"UggbiKZthuOhJXgCoAEC","text":"58:00?","time":"5 years ago","author":"marko klein","channel":"UC175wQktpp8FcWQgrmHREbw","votes":"1","photo":"https:\/\/yt3.ggpht.com\/ytc\/AKedOLQBlwzQV2QIM72NL_Dput4GBJL5oQs0-Qpxrw=s176-c-k-c0x00ffffff-no-rj","heart":false},{"id_val":"bmJqPnV3Jrw","cid":"UgidHcE4NzM653gCoAEC","text":"1:14:00 ????????","time":"5 years ago","author":"Techno experience","channel":"UCg4QRCIPBzshu0SwU7g-87g","votes":"10","photo":"https:\/\/yt3.ggpht.com\/ytc\/AKedOLRl1pABk9qSS0n_-jNoMpdoo8sSxvWtWX5JNfzfLg=s176-c-k-c0x00ffffff-no-rj","heart":false},{"id_val":"bmJqPnV3Jrw","cid":"Ugxr0J7xYE3gRySxJAJ4AaABAg","text":"1:06 ??","time":"4 years ago","author":"Lorenzo Zuliani","channel":"UCk9JIRZOwWnyQBRpTLT6cyA","votes":"0","photo":"https:\/\/yt3.ggpht.com\/ytc\/AKedOLQvQw4XvIEUg-kQHJj3Pz7egP7D3D84y59iOHQ8=s176-c-k-c0x00ffffff-no-rj","heart":false},{"id_val":"bmJqPnV3Jrw","cid":"UgxmLDOFkKdXylqZUXV4AaABAg","text":"1:32?","time":"4 years ago","author":"Megan Richards","channel":"UC-Z6CTJD-c-wxNfdwjCaXOw","votes":"0","photo":"https:\/\/yt3.ggpht.com\/ytc\/AKedOLSUyPSahruZ5YzlGtPZ1WKF-vHMjjL_W3PkXA=s176-c-k-c0x00ffffff-no-rj","heart":false},{"id_val":"bmJqPnV3Jrw","cid":"UghoWbBtOKYhxXgCoAEC","text":"1:08:48 from? tiqui tiqui tiqui tiqui ?","time":"5 years ago","author":"Alberto alducin","channel":"UC6mdtiRixBqoa1sNRqh5L6w","votes":"3","photo":"https:\/\/yt3.ggpht.com\/ytc\/AKedOLRixXJLaKwrje5ZFFeWLhjlZcV6zK0LLDa73qYBbg=s176-c-k-c0x00ffffff-no-rj","heart":false}]