[{"id_val":"Cs-yIdjv15E","cid":"UgxB4BW2TlXK2bqXx6t4AaABAg","text":"Tracklist:\n1st Regal - Burning Old Idols, coming on 2nd July ;)\n4:21 Kander - Red Brick \n10:40 Regal - She dances alone \n20:00 Geerson - Keep inside\n23:20 Lucass P - The Imposter\n25:07 Regal - Before I Die (Ft. Pau Castro) \n28:00 Marie Davidson - 'Workaholic Paranoid Bitch' + Maxime Iko - In Utero (in the background)\n30:30 RUN DMC, Jason Nevins - It's Like That (COPYRIGHT CLAME) \n34:00 Planetary Assault Systems - Say it Loud (Token)\n37:20 Regal - True Spirit (coming soon)\n44:15 Covenant - Call the ships to port (Club Version)","time":"6 months ago (edited)","author":"The V3lesa","channel":"UCU163-tXV1mYhjl12HNSIxQ","votes":"91","photo":"https:\/\/yt3.ggpht.com\/ytc\/AKedOLTU0xK99pc9_UI-C6umGpt2FgglvVoM1Nlt-4A1=s176-c-k-c0x00ffffff-no-rj","heart":false},{"id_val":"Cs-yIdjv15E","cid":"UgzJUvYUnX1Pc95B4QB4AaABAg","text":"46:13 fantastic track","time":"6 months ago","author":"last boy scout","channel":"UCgjr--fa-QTm_btigZuNTbQ","votes":"4","photo":"https:\/\/yt3.ggpht.com\/ytc\/AKedOLTWfa4acqDaScKISg10E2Gion_32CVfSc1McJsIhQ=s176-c-k-c0x00ffffff-no-rj","heart":false},{"id_val":"Cs-yIdjv15E","cid":"Ugw2vmXAONcDyPLTEoB4AaABAg","text":"28:49 a\u00ed \u00e9 aulasssss \ud83d\udc4f\ud83d\udc4f\ud83d\udc4f","time":"3 months ago","author":"Douglas Amaral","channel":"UCivLiF4vMcbn4q1mdU5N6rQ","votes":"0","photo":"https:\/\/yt3.ggpht.com\/ytc\/AKedOLROo9zhRRJAvqa_uyKGPQi8i8AWh4vtcnTOoZuu7Q=s176-c-k-c0x00ffffff-no-rj","heart":false},{"id_val":"Cs-yIdjv15E","cid":"UgxB4BW2TlXK2bqXx6t4AaABAg.9OjisVUvZ379OmL_FvPMbY","text":"28:00 Marie Davidson - 'Workaholic Paranoid Bitch' some kind of remix","time":"6 months ago","author":"Nikola Pantovic","channel":"UCZrNNlgRxZBQmWuyMWipQtw","votes":"2","photo":"https:\/\/yt3.ggpht.com\/ytc\/AKedOLSFwYADnkUETDpyYopuUOF4wHhhdGXvBzlWqV2GEA=s176-c-k-c0x00ffffff-no-rj","heart":false},{"id_val":"Cs-yIdjv15E","cid":"UgxB4BW2TlXK2bqXx6t4AaABAg.9OjisVUvZ379OpQS-q5fw-","text":"23:20 Lucass P - The Imposter","time":"6 months ago","author":"Rodrigo Omatos","channel":"UCnP12wpS2a-kvd9kdaNOhJg","votes":"1","photo":"https:\/\/yt3.ggpht.com\/ytc\/AKedOLQBdOUAGsKK0Gy2bBJ2HxMcM7vDL5hhq2UeVfzI2A=s176-c-k-c0x00ffffff-no-rj","heart":false},{"id_val":"Cs-yIdjv15E","cid":"UgxB4BW2TlXK2bqXx6t4AaABAg.9OjisVUvZ379OqV5oEVFlV","text":"45:00 covenant- call the ships to port","time":"6 months ago","author":"kingmax","channel":"UCri-A3qIn-1xEdcaE0HKGIQ","votes":"0","photo":"https:\/\/yt3.ggpht.com\/ytc\/AKedOLQdB2XT-Lp_P9SXIPgmb7gQYBEuMu91HXUpkBKwLQ=s176-c-k-c0x00ffffff-no-rj","heart":false},{"id_val":"Cs-yIdjv15E","cid":"UgxB4BW2TlXK2bqXx6t4AaABAg.9OjisVUvZ379OqyPlSqW37","text":"40:40 pleaaasee? Thanks","time":"6 months ago","author":"Elgallu Gallu","channel":"UCC2qZcqJ9x5skOLQ73Hl6dg","votes":"1","photo":"https:\/\/yt3.ggpht.com\/ytc\/AKedOLTBELQqWNBnG55OXXrjQGPoINpZIZVeewKTUGvP=s176-c-k-c0x00ffffff-no-rj","heart":false},{"id_val":"Cs-yIdjv15E","cid":"UgxB4BW2TlXK2bqXx6t4AaABAg.9OjisVUvZ379P3lLBiyV9w","text":"9:10 Hioll - You May Feel Panicky","time":"6 months ago","author":"Victor Ticolis","channel":"UCBEvrWaqgUiirchqaWl4hIw","votes":"1","photo":"https:\/\/yt3.ggpht.com\/ytc\/AKedOLTHS0ihHJfat0q8PFwYfefbwTz6N5VqdObTXlXQ=s176-c-k-c0x00ffffff-no-rj","heart":false},{"id_val":"Cs-yIdjv15E","cid":"UgxB4BW2TlXK2bqXx6t4AaABAg.9OjisVUvZ379P_eNeJeUad","text":"34:00 Planetary Assault Systems - Say it Loud (Token)","time":"6 months ago","author":"Gui Lad","channel":"UCShchOjCusfSgmAg5sDKb-A","votes":"1","photo":"https:\/\/yt3.ggpht.com\/ytc\/AKedOLRQHZZL_ptMpjkWnGbIF9RVB8ToyjzQRlUVpL2qgyI=s176-c-k-c0x00ffffff-no-rj","heart":false},{"id_val":"Cs-yIdjv15E","cid":"UgwYqlu3VxCH79S5vQx4AaABAg","text":"25:00 this is the ultimate 2021 bomb, thanks, Regal!","time":"6 months ago","author":"Flavio R. David","channel":"UC4MQd4WJPjg_-x34_mg0Ktw","votes":"17","photo":"https:\/\/yt3.ggpht.com\/ytc\/AKedOLRSAdjCzmSXfIuv48smiZez1bPSPDtxUPUQe0xHoBM=s176-c-k-c0x00ffffff-no-rj","heart":false},{"id_val":"Cs-yIdjv15E","cid":"Ugz86d1qSlJu1HfR6ZZ4AaABAg","text":"13:50 one of the best techno 2021 \ud83d\ude0d\ud83d\ude0d","time":"6 months ago","author":"Nicol\u00e1s","channel":"UCLViWTxXMVbAGZaj_t4-hpQ","votes":"1","photo":"https:\/\/yt3.ggpht.com\/u73AywvjWjXvUUgJOv5WXyN6zpvYz6kvzrMH5DlIw8Yi1G3rMNXb5ZR0aX1LH8xu40M6ArVZ1A=s176-c-k-c0x00ffffff-no-rj","heart":false},{"id_val":"Cs-yIdjv15E","cid":"UgwYqlu3VxCH79S5vQx4AaABAg.9Om5ljFLz-p9Oofn9Lkyvl","text":"Track id???","time":"6 months ago","author":"Lasha Udzilauri","channel":"UCexTBL1OiZFsXt5BcYg6yyA","votes":"0","photo":"https:\/\/yt3.ggpht.com\/ytc\/AKedOLTALEw2-LdxwLt_0EHJ4rBy_CivZy83P504gbqD_g=s176-c-k-c0x00ffffff-no-rj","heart":false},{"id_val":"Cs-yIdjv15E","cid":"Ugwn5DPMQKLLF-AhL3V4AaABAg","text":"35:00 anyone? Fucking stomper \ud83d\udd25\ud83d\udd25\ud83d\udd25","time":"6 months ago","author":"Dan Vakhitoff","channel":"UCEfzHV_wCiVMgi2RPh_d9mA","votes":"0","photo":"https:\/\/yt3.ggpht.com\/ytc\/AKedOLQPhbnwaV2LZRLWLp-NUUvENmV30pnKiqQXJcx3Rg=s176-c-k-c0x00ffffff-no-rj","heart":false},{"id_val":"Cs-yIdjv15E","cid":"Ugxjw0z6C3_MYQqxKI14AaABAg","text":"17:20 track ID????????","time":"6 months ago","author":"Tim Rood","channel":"UCU1IdyKvw9cs01xWzdVoh4Q","votes":"1","photo":"https:\/\/yt3.ggpht.com\/ytc\/AKedOLRjnEhM5ko796cBTcvWUKoM-XY7r18wbCXsP2CaDEI=s176-c-k-c0x00ffffff-no-rj","heart":false},{"id_val":"Cs-yIdjv15E","cid":"Ugz5pTg5BNho_Dx2A_R4AaABAg","text":"30:30 what's a track?","time":"6 months ago","author":"\u0413\u043e\u043b\u043e\u0432\u0430 \u0434\u043e\u043a\u0442\u043e\u0440\u0430 \u0411\u0430\u0443\u0435\u0440\u0430","channel":"UCi2bLvGo6l64_ijCkP-4eRg","votes":"3","photo":"https:\/\/yt3.ggpht.com\/ytc\/AKedOLSi2VQrXZs5D0ZqVYLUoLEqhf9eovrTsBvaUFc6Aw=s176-c-k-c0x00ffffff-no-rj","heart":false},{"id_val":"Cs-yIdjv15E","cid":"Ugz2Ll-N6z_4HvhkC4p4AaABAg","text":"46:40 ID please!! \ud83d\ude4f \ud83d\ude0d\u2764\ufe0f","time":"6 months ago","author":"Daniel Franco","channel":"UCm1VgyXZ3AjSrLPj1kbgZpQ","votes":"1","photo":"https:\/\/yt3.ggpht.com\/ytc\/AKedOLSAsq-kKTI3du9cnR1o0342npu2uS9Qq2cknVxT=s176-c-k-c0x00ffffff-no-rj","heart":false},{"id_val":"Cs-yIdjv15E","cid":"UgziCuB9lg4-bmRkdLF4AaABAg","text":"27:26 yes beesh gimme some","time":"6 months ago","author":"Isabella Calderone","channel":"UCRIR_o6TUU3I-WA8aeK99_A","votes":"1","photo":"https:\/\/yt3.ggpht.com\/ytc\/AKedOLQTjt1_E1CP1TX1CtVRw5ZtLLzeC1IsHacj9qG2jw=s176-c-k-c0x00ffffff-no-rj","heart":false},{"id_val":"Cs-yIdjv15E","cid":"Ugyc0OguNCCssH18z3h4AaABAg","text":"18:20 id??????","time":"3 months ago","author":"Srdjan Pajic","channel":"UCx9-kQwpnEkPVdlOj-JRstg","votes":"0","photo":"https:\/\/yt3.ggpht.com\/ytc\/AKedOLTMyqJllvSLNYVfdVskYgA6y2nbRs67cnl7hqPBlQ=s176-c-k-c0x00ffffff-no-rj","heart":false},{"id_val":"Cs-yIdjv15E","cid":"Ugwvi5za8qLesKxT5Kl4AaABAg","text":"31:50","time":"3 months ago","author":"\u03b7\u03c9 \u03b7\u03c5","channel":"UCw14wjhE8HKYq_iDL4FSD1A","votes":"0","photo":"https:\/\/yt3.ggpht.com\/ytc\/AKedOLTWB4lBgCpYBOjf_cXHO0mSXEu09rQ4eRW3GAaUcw=s176-c-k-c0x00ffffff-no-rj","heart":false},{"id_val":"Cs-yIdjv15E","cid":"UgwMlWBy6gcI9dpjTOJ4AaABAg","text":"9:00? \u26cf\u26cf","time":"6 months ago","author":"Giuseppe Mastrangelo","channel":"UCnELxI6zWb-FqYOCOSmfjIQ","votes":"0","photo":"https:\/\/yt3.ggpht.com\/ytc\/AKedOLTMwrsSTmZ2vUGnAL-RC2U3TKOsLynkJ57aLg=s176-c-k-c0x00ffffff-no-rj","heart":false},{"id_val":"Cs-yIdjv15E","cid":"UgzZw6t2LUi2CzZcAPt4AaABAg","text":"15:00 please","time":"6 months ago","author":"Rhys N","channel":"UCTbuHw6Ao66Ziz0gtWPNi7Q","votes":"4","photo":"https:\/\/yt3.ggpht.com\/ytc\/AKedOLTb3TEa-GSu6SaILPilqrEgiNj1wwZeLZsd9w=s176-c-k-c0x00ffffff-no-rj","heart":false}]