[{"id_val":"huQRjcuX2MY","cid":"Ugz955zEH98VFoped954AaABAg","text":"Tracklist, great set\ud83d\udd25\ud83d\udd25\u2764\ufe0f\n00:46 Phurpa - 02.3\n01:30 ????\n04:30 Alienage - Filter Funkard\n08:37 Philou Louzolo - Ahosi Army\n11:06 Roger That - How Does It Feel\n16:50 Ben Buitendijk - Erosion\n20:04 Perm - Foralapp Quokium I\n23:43 Carpainter - Back 2 Acid\n28:05 Privacy - Make Yr Transition\n33:10 Macchina Nera - Hunting Nightly (Reformed Society Rmx)\n36:16 Benales - Sit Fence\n38:30 Arthur Robert - Cautious\n43:15 Dirty Princess - Jugar Al Rev\u00e9s\n46:23 Adriano Canzian - Macho Boy (Pink RMX)\n50:40 DJ Haus - Metrophosis\n54:04 The O.T. Quartet - Hold That Sucker Down (Builds Like A Skyscraper)\n57:55 Madonna - Nothing Really Matters","time":"1 year ago (edited)","author":"getbakedtonight","channel":"UCnT_Y3fKXaxhX_0HoCfz9qA","votes":"76","photo":"https:\/\/yt3.ggpht.com\/ytc\/AKedOLRU9LDORzOW2DmqXOBMMAQTRhs692shdcGhMe72=s176-c-k-c0x00ffffff-no-rj","heart":false},{"id_val":"huQRjcuX2MY","cid":"UgxqUXva0yx8qCb60X54AaABAg","text":"58:36 that happy hip wiggle <33 mwah x","time":"1 year ago","author":"Thea Shields","channel":"UC7K-z8WRtzBbv6_lWMqtvoQ","votes":"3","photo":"https:\/\/yt3.ggpht.com\/ytc\/AKedOLQslJ_zu50ZZEIjihiOx8yHRResZDAE8FQYOLqG=s176-c-k-c0x00ffffff-no-rj","heart":false}]