[{"id_val":"JkkDKuiqVhs","cid":"Ugzh0utVsRuDuYqNzUx4AaABAg","text":"18:35 Ryan loves this bassline and so do we. Thank you Shanti! <3 \u207d\u1d43\u207f\u02b8\u1d47\u1d52\u1d48\u02b8 \u1d4d\u1d52\u1d57 \u1d43\u207f \u1da6\u1d48\u02c0\u207e","time":"1 year ago (edited)","author":"Alexandre Roux","channel":"UCgKfRaO6KwjQG36x4XIx8gg","votes":"0","photo":"https:\/\/yt3.ggpht.com\/ytc\/AKedOLQWBDNC_5GRjc-5ki1PMlqDFdOMdE3EhEFo4HCE=s176-c-k-c0x00ffffff-no-rj","heart":false},{"id_val":"JkkDKuiqVhs","cid":"UgwHtFGouFe9oR-7CiN4AaABAg.9ERsw2EAhoJ9ETAErIZ_tD","text":"1:25:45 is DJ Texta - Play it Deejay","time":"1 year ago","author":"Sliimbo96","channel":"UCmR2JXcU_mHnKrmzGho53_Q","votes":"3","photo":"https:\/\/yt3.ggpht.com\/ytc\/AKedOLROs4ubDmku7S0AWyFhc1UMMYeP3EAURbwz6Q=s176-c-k-c0x00ffffff-no-rj","heart":false},{"id_val":"JkkDKuiqVhs","cid":"UgwHtFGouFe9oR-7CiN4AaABAg.9ERsw2EAhoJ9ETCuBf0xcu","text":"41:25 Elliot Adamson - No Chill (Original Mix)","time":"1 year ago","author":"Thomas Hawer","channel":"UCMTJGe4OUJJbsoj5a7L_TMw","votes":"1","photo":"https:\/\/yt3.ggpht.com\/ytc\/AKedOLRB1Ozm3JYY2lGdOvG9KVY1bvpmRrfU2Yuq0Q=s176-c-k-c0x00ffffff-no-rj","heart":false},{"id_val":"JkkDKuiqVhs","cid":"UgwHtFGouFe9oR-7CiN4AaABAg.9ERsw2EAhoJ9ETD6bKPwMw","text":"47:45 Jovonn feat. Casioware - Turnin Me Out (Original Mix)","time":"1 year ago","author":"Thomas Hawer","channel":"UCMTJGe4OUJJbsoj5a7L_TMw","votes":"2","photo":"https:\/\/yt3.ggpht.com\/ytc\/AKedOLRB1Ozm3JYY2lGdOvG9KVY1bvpmRrfU2Yuq0Q=s176-c-k-c0x00ffffff-no-rj","heart":false},{"id_val":"JkkDKuiqVhs","cid":"UgwHtFGouFe9oR-7CiN4AaABAg.9ERsw2EAhoJ9ETDFaLhQWl","text":"1:54:00 rRoxymore \" Soleil Synthetique \"","time":"1 year ago (edited)","author":"morediscus","channel":"UCE17JGux7t_PO0EFZJKiwaA","votes":"2","photo":"https:\/\/yt3.ggpht.com\/ytc\/AKedOLRaRpNEZbvCFwgbkIFC5hy1bsmrLwzzJ4_8sQ=s176-c-k-c0x00ffffff-no-rj","heart":false},{"id_val":"JkkDKuiqVhs","cid":"UgwHtFGouFe9oR-7CiN4AaABAg.9ERsw2EAhoJ9ETXRltGPjS","text":"1:25:45 DJ Texta & Persian - Play It Deejay","time":"1 year ago","author":"{ deserving }","channel":"UCU07lz1U7Np5G_3FuNhcKZw","votes":"2","photo":"https:\/\/yt3.ggpht.com\/ytc\/AKedOLQcph43JXc-jD75Mm2Y0R4i3xfBB1AgcBOmNgDvwA=s176-c-k-c0x00ffffff-no-rj","heart":false},{"id_val":"JkkDKuiqVhs","cid":"UgwHtFGouFe9oR-7CiN4AaABAg.9ERsw2EAhoJ9ETlKmL0pE2","text":"30:00 Michael J Blood - Track 11 from the introducing mixtape on 2 B Real","time":"1 year ago","author":"Alex Gillespie","channel":"UCF2T0UkZ2anYJ7p_nVxDs0Q","votes":"5","photo":"https:\/\/yt3.ggpht.com\/ytc\/AKedOLRNpvJjIgw0luuTFYSQx04FSjpOodfC-xi9Pbn_7g=s176-c-k-c0x00ffffff-no-rj","heart":false},{"id_val":"JkkDKuiqVhs","cid":"UgwHtFGouFe9oR-7CiN4AaABAg.9ERsw2EAhoJ9EToSkJzpk_","text":"1:07:50  Jackson Ryland - Blaze Freak","time":"1 year ago","author":"Oliver","channel":"UCYZvSkvHxgdUZdoXZL5ti6Q","votes":"3","photo":"https:\/\/yt3.ggpht.com\/ytc\/AKedOLQWW2w1EFKCG2F5tgQXD9QKa4bhuwRVdQpGzw=s176-c-k-c0x00ffffff-no-rj","heart":false},{"id_val":"JkkDKuiqVhs","cid":"UgwHtFGouFe9oR-7CiN4AaABAg.9ERsw2EAhoJ9EiuLaizIJl","text":"1:38:00 is hodge - lanacut (shanti Celeste remix)\n\nIt\u2019s unreleased Moxie played it on her NTS show","time":"1 year ago","author":"ollie wheeler","channel":"UCmsOqzMO7hnik0eg83lFmqg","votes":"3","photo":"https:\/\/yt3.ggpht.com\/ytc\/AKedOLTGt5dEN_XnQpInvTCOH7XnxlzQA5x0p7RnPSRU=s176-c-k-c0x00ffffff-no-rj","heart":false},{"id_val":"JkkDKuiqVhs","cid":"UgwHtFGouFe9oR-7CiN4AaABAg.9ERsw2EAhoJ9EyarfLav2s","text":"7:30  Dj Kemit - Forbidden love","time":"1 year ago (edited)","author":"Roy Sethi","channel":"UCsQFLfvJpKxoIYWz1ZN1iNQ","votes":"1","photo":"https:\/\/yt3.ggpht.com\/ytc\/AKedOLQgZWbuCDNNBwXcsU5osJ9NbpK2CoRZdZmBpA=s176-c-k-c0x00ffffff-no-rj","heart":false},{"id_val":"JkkDKuiqVhs","cid":"UgwHtFGouFe9oR-7CiN4AaABAg.9ERsw2EAhoJ9EybSjAAveL","text":"15:00  Jay Ka - How do you stay young","time":"1 year ago (edited)","author":"Roy Sethi","channel":"UCsQFLfvJpKxoIYWz1ZN1iNQ","votes":"1","photo":"https:\/\/yt3.ggpht.com\/ytc\/AKedOLQgZWbuCDNNBwXcsU5osJ9NbpK2CoRZdZmBpA=s176-c-k-c0x00ffffff-no-rj","heart":false},{"id_val":"JkkDKuiqVhs","cid":"UgwHtFGouFe9oR-7CiN4AaABAg.9ERsw2EAhoJ9Eyd6bDC24a","text":"1:29:10 Jackson Ryland - Aloe Vera","time":"1 year ago","author":"Roy Sethi","channel":"UCsQFLfvJpKxoIYWz1ZN1iNQ","votes":"3","photo":"https:\/\/yt3.ggpht.com\/ytc\/AKedOLQgZWbuCDNNBwXcsU5osJ9NbpK2CoRZdZmBpA=s176-c-k-c0x00ffffff-no-rj","heart":false},{"id_val":"JkkDKuiqVhs","cid":"UgwHtFGouFe9oR-7CiN4AaABAg.9ERsw2EAhoJ9F-f9hrS8Cw","text":"1:50:25 Mr. G - House Attack","time":"1 year ago","author":"Roy Sethi","channel":"UCsQFLfvJpKxoIYWz1ZN1iNQ","votes":"1","photo":"https:\/\/yt3.ggpht.com\/ytc\/AKedOLQgZWbuCDNNBwXcsU5osJ9NbpK2CoRZdZmBpA=s176-c-k-c0x00ffffff-no-rj","heart":false},{"id_val":"JkkDKuiqVhs","cid":"UgwHtFGouFe9oR-7CiN4AaABAg.9ERsw2EAhoJ9F25HPz-IU4","text":"1:41:35 is Corporeal Face - Visions on tone dropout vol. 9!! banger","time":"1 year ago","author":"FJD","channel":"UCDGisBhlb-m0qndGS3kx5pQ","votes":"1","photo":"https:\/\/yt3.ggpht.com\/ytc\/AKedOLRkusVU_cVFPLwB23pIVJL-2C-CSmjre8fpoTab=s176-c-k-c0x00ffffff-no-rj","heart":false},{"id_val":"JkkDKuiqVhs","cid":"UgwHtFGouFe9oR-7CiN4AaABAg.9ERsw2EAhoJ9FBtQADEygT","text":"1:33:45 Black Spirits - Hey Hey (Kings Of Soul Dub)","time":"1 year ago","author":"Rok Torkar","channel":"UCKlBuUoUvWsdBiZXKCrU1xw","votes":"4","photo":"https:\/\/yt3.ggpht.com\/ytc\/AKedOLTP9BfAsjF22Bq8h_zwmwJr7enXyW2GGCBQpPma=s176-c-k-c0x00ffffff-no-rj","heart":false},{"id_val":"JkkDKuiqVhs","cid":"UgwHtFGouFe9oR-7CiN4AaABAg.9ERsw2EAhoJ9FOvPH8rgwF","text":"22:40 ? Masterpiece....","time":"1 year ago","author":"Khaos Aurae","channel":"UCNEo4IJrRr-dVhUlIbgh6tw","votes":"1","photo":"https:\/\/yt3.ggpht.com\/ytc\/AKedOLQ5ptrTCKtxxD8hqs6bD9y1DRi1lWStGiBb0DkHqg=s176-c-k-c0x00ffffff-no-rj","heart":false},{"id_val":"JkkDKuiqVhs","cid":"UgwHtFGouFe9oR-7CiN4AaABAg.9ERsw2EAhoJ9K4k4-hMCd3","text":"1:11:20 is Steve Robbins - The Power Of","time":"10 months ago","author":"getbakedtonight","channel":"UCnT_Y3fKXaxhX_0HoCfz9qA","votes":"1","photo":"https:\/\/yt3.ggpht.com\/ytc\/AKedOLRU9LDORzOW2DmqXOBMMAQTRhs692shdcGhMe72=s176-c-k-c0x00ffffff-no-rj","heart":false},{"id_val":"JkkDKuiqVhs","cid":"UgyptrIbPAGoN5I-T3B4AaABAg","text":"03:20 SHEA AUDIO - Soreal (SHEA 001) \nReally rocks. Got it on vinyl...","time":"1 year ago","author":"Bojan Pantic","channel":"UCLkSKdp-ZhZtRWlACiPvYEA","votes":"0","photo":"https:\/\/yt3.ggpht.com\/ytc\/AKedOLS5MFvqzGSB2kgz4Uag_TgdIBGX4CqXzSWzMA=s176-c-k-c0x00ffffff-no-rj","heart":false},{"id_val":"JkkDKuiqVhs","cid":"UgyuwD8QgMSRIstaP-h4AaABAg","text":"1:20:05 what a romper!","time":"1 year ago","author":"Courtney Armstrong- Clark","channel":"UC2YM9gX9paxmteOJP2nqpQw","votes":"23","photo":"https:\/\/yt3.ggpht.com\/ytc\/AKedOLRZnImrNJEHDWJ9W_Z-vLhdq1uh_LVd-lfdZ4-X_A=s176-c-k-c0x00ffffff-no-rj","heart":false},{"id_val":"JkkDKuiqVhs","cid":"Ugywb9MrGtKMDvFe51p4AaABAg.9EaKN4KKgUR9FQQFNdTFky","text":"1:11:00 sounds like something Faith Beat would release","time":"1 year ago","author":"Scout","channel":"UC_MAgtuIg2lI-YmfzeRWDyQ","votes":"2","photo":"https:\/\/yt3.ggpht.com\/ytc\/AKedOLRR0EmFW-hIjnATxzNPl847TCJCqUr8hEfWMYCl=s176-c-k-c0x00ffffff-no-rj","heart":false},{"id_val":"JkkDKuiqVhs","cid":"UgzNwGmRxmHQ_8qCBkx4AaABAg","text":"23:00 would be amazing if anyone has it","time":"1 year ago","author":"FJD","channel":"UCDGisBhlb-m0qndGS3kx5pQ","votes":"3","photo":"https:\/\/yt3.ggpht.com\/ytc\/AKedOLRkusVU_cVFPLwB23pIVJL-2C-CSmjre8fpoTab=s176-c-k-c0x00ffffff-no-rj","heart":false},{"id_val":"JkkDKuiqVhs","cid":"UgzgRb6qxEJBOfPLF_t4AaABAg","text":"1:06:50 classic \ud83e\udd72. happens to everyone","time":"5 months ago","author":"Oscar Palomino","channel":"UCUiRmRRtkzOxLPXSAY9LBUg","votes":"0","photo":"https:\/\/yt3.ggpht.com\/ytc\/AKedOLQwx9AYO3NzTtQ1K70mJE5vftY4AM9HSXVS4a3J6w=s176-c-k-c0x00ffffff-no-rj","heart":false},{"id_val":"JkkDKuiqVhs","cid":"Ugzdq6c-tyACfW_lNQ14AaABAg","text":"1:34:30 cant stop dancing!! \n\nID?\n\nedit: ID is Black Spirit - Hey Hey (Kings Of Soul Dub)","time":"1 year ago (edited)","author":"Aynar von Fiehlen","channel":"UCFRTe2zegxdLfTR9GQNivKQ","votes":"37","photo":"https:\/\/yt3.ggpht.com\/ytc\/AKedOLTkc-1SBMBj1Syq1JZSobsVbDFTUb0U8mqq8Z4oMg=s176-c-k-c0x00ffffff-no-rj","heart":false},{"id_val":"JkkDKuiqVhs","cid":"Ugxi3WWcaMPqZS1ZGqp4AaABAg","text":"1:11:20 : If anyone could hit me up on this one, that would be amazing \u2764","time":"1 year ago (edited)","author":"Vincent ROUSSET","channel":"UCl5yJz51JUTXUf2EBDmZ7oA","votes":"2","photo":"https:\/\/yt3.ggpht.com\/ytc\/AKedOLTtZTTV493N13CaichW7MrY-w_IjvXrnjNcpA=s176-c-k-c0x00ffffff-no-rj","heart":false},{"id_val":"JkkDKuiqVhs","cid":"Ugw5d1Fz0f_wHkEblHV4AaABAg","text":"1:29:40 track id anyone? insanely good!","time":"1 year ago","author":"xpomosoma","channel":"UC0YkE78-up7WwdWzolKpe3w","votes":"1","photo":"https:\/\/yt3.ggpht.com\/ytc\/AKedOLTryFB89G7pLsL6Cfd9B19VVlx3NgPQVEbwpA=s176-c-k-c0x00ffffff-no-rj","heart":false},{"id_val":"JkkDKuiqVhs","cid":"UgxcMy7D1SLeFBzx_sZ4AaABAg","text":"1:11:47 - Let's go \ud83d\udd25","time":"1 year ago","author":"Vincent ROUSSET","channel":"UCl5yJz51JUTXUf2EBDmZ7oA","votes":"1","photo":"https:\/\/yt3.ggpht.com\/ytc\/AKedOLTtZTTV493N13CaichW7MrY-w_IjvXrnjNcpA=s176-c-k-c0x00ffffff-no-rj","heart":false},{"id_val":"JkkDKuiqVhs","cid":"UgwKkLQpa2rKPizLoo14AaABAg","text":"Track ID at 1:34:30?","time":"1 year ago","author":"Michael Merwin","channel":"UCZh0A-2EH5ErshkCOgAvwIg","votes":"6","photo":"https:\/\/yt3.ggpht.com\/ytc\/AKedOLTxHx_yoevtBBtRQOgxPYzhUXTbRRDpkYkT7kfs4w=s176-c-k-c0x00ffffff-no-rj","heart":false},{"id_val":"JkkDKuiqVhs","cid":"UgzZSAYUladUSi-YIgF4AaABAg","text":"1:19:00 !!!!","time":"1 year ago","author":"mc","channel":"UCiFPTjm4YOhgfaCAGE2VunQ","votes":"3","photo":"https:\/\/yt3.ggpht.com\/ytc\/AKedOLSp4IS2RGYuuFXVnlRjdwcG0F0sSfZBhtlgvA=s176-c-k-c0x00ffffff-no-rj","heart":false},{"id_val":"JkkDKuiqVhs","cid":"UgxPfqK398jL4Go-voJ4AaABAg","text":"1:11:00 track id?","time":"1 year ago","author":"Juan Tom\u00e1s Albornoz","channel":"UCemXfFJx5FmZnuMJ32v0mow","votes":"0","photo":"https:\/\/yt3.ggpht.com\/ytc\/AKedOLSQS2E_jRTk7obgjN6YAnqTFDD8w3yNGVe5PSntpw=s176-c-k-c0x00ffffff-no-rj","heart":false},{"id_val":"JkkDKuiqVhs","cid":"Ugz_cBcc6_bZsWvWTRp4AaABAg.9EsisIh7a6s9Etse2exmpH","text":"1:00:00 here: https:\/\/youtu.be\/cEGbLwlKZ54\nOnly a mixed version is available, its mixed on vinyl too...\nCan\u2019t believe I didn\u2019t notice the tag at 36:01 until now, its all over the mix...im stupid.","time":"1 year ago (edited)","author":"getbakedtonight","channel":"UCnT_Y3fKXaxhX_0HoCfz9qA","votes":"0","photo":"https:\/\/yt3.ggpht.com\/ytc\/AKedOLRU9LDORzOW2DmqXOBMMAQTRhs692shdcGhMe72=s176-c-k-c0x00ffffff-no-rj","heart":false},{"id_val":"JkkDKuiqVhs","cid":"Ugz5aqD0CgzPXGJudf14AaABAg","text":"1:19:00 id??","time":"1 year ago","author":"Alistair Dunlop","channel":"UCugjfXox4k0pLGLgA3sJzyw","votes":"7","photo":"https:\/\/yt3.ggpht.com\/ytc\/AKedOLQ1vdSStJODoHefPdgrsJUrO7p-N7KwxNa6Lg=s176-c-k-c0x00ffffff-no-rj","heart":false},{"id_val":"JkkDKuiqVhs","cid":"Ugz88olBojlD0iC5GRB4AaABAg","text":"56:30 ???? Please help","time":"1 year ago","author":"WACBOY","channel":"UC6YpC4YFoS-euliZmEgc-zA","votes":"1","photo":"https:\/\/yt3.ggpht.com\/ytc\/AKedOLSnIZm81qzq2Zr_3Dpuva4gk7d-BBqLGo9k9g=s176-c-k-c0x00ffffff-no-rj","heart":false},{"id_val":"JkkDKuiqVhs","cid":"UgxSEDBZidUWOGHwrDV4AaABAg","text":"Track 47:30?","time":"1 year ago","author":"edsbrant1","channel":"UC2Luy-cPVExGIpVbD4OdxqQ","votes":"0","photo":"https:\/\/yt3.ggpht.com\/ytc\/AKedOLRlIZ_lTn9qM0iGZi1TSsO_k2jpytNaPD7stU_X=s176-c-k-c0x00ffffff-no-rj","heart":false},{"id_val":"JkkDKuiqVhs","cid":"UgwB7z7k6Mnh7qy-Bep4AaABAg","text":"03:20????","time":"1 year ago","author":"Leo Orso","channel":"UCjT8Hfmt0pNPLru5hTwc7XA","votes":"0","photo":"https:\/\/yt3.ggpht.com\/ytc\/AKedOLQaa8AOZdEPVTkwm1z-wRdK2Qys-KLk0ILVU2PhmQ=s176-c-k-c0x00ffffff-no-rj","heart":false}]