[{"id_val":"jYL7_4BV9T8","cid":"UgyX5dBJDjn3bAh7-w14AaABAg","text":"51:06 is just the best part","time":"3 months ago","author":"John Ross","channel":"UCiffO7FhiTo8b-cg-49DuYg","votes":"1","photo":"https:\/\/yt3.ggpht.com\/ytc\/AKedOLQ0c1qqAMcZ5n1RSmFnBvLm0aujyDzcUG0SKiLY=s176-c-k-c0x00ffffff-no-rj","heart":false},{"id_val":"jYL7_4BV9T8","cid":"Ugwid6bHds7TbSDjK454AaABAg","text":"15:33 id pls ?","time":"3 months ago","author":"\u0422\u0438\u043c\u0443\u0440 \u0423\u0441\u043c\u0430\u043d\u043e\u0432","channel":"UCaHNPFXyNCr4YYBM3vMHphA","votes":"0","photo":"https:\/\/yt3.ggpht.com\/ytc\/AKedOLSTpdL-4CKI-eUEi0AzpWSrbYK-Krpk8JUd9g=s176-c-k-c0x00ffffff-no-rj","heart":false}]