[{"id_val":"KKW6k0BTcKA","cid":"Ugz4ETR7boDmIU9VPB14AaABAg","text":"07:00 Ch\u00e9 - The Incident (Wet Dream Mix) [MMLP010]","time":"2 weeks ago","author":"Egal Egal","channel":"UCtX1Pv_xirdNwtwm_8bzZiw","votes":"3","photo":"https:\/\/yt3.ggpht.com\/ytc\/AKedOLRMoGz6syDXRIKhfhRaa3-zN-Z8M5VPRYOFqw=s176-c-k-c0x00ffffff-no-rj","heart":false},{"id_val":"KKW6k0BTcKA","cid":"Ugw2UvSkWu2Q7msueTB4AaABAg","text":"44:00 Dario Zenker - Hassel [ESPERANZA022]","time":"2 weeks ago","author":"Egal Egal","channel":"UCtX1Pv_xirdNwtwm_8bzZiw","votes":"2","photo":"https:\/\/yt3.ggpht.com\/ytc\/AKedOLRMoGz6syDXRIKhfhRaa3-zN-Z8M5VPRYOFqw=s176-c-k-c0x00ffffff-no-rj","heart":false},{"id_val":"KKW6k0BTcKA","cid":"Ugxz8Z_AcV1s_We-5lN4AaABAg","text":"40:00 This Side Up - Love Starts With An L [CRMLP027]","time":"2 weeks ago","author":"Egal Egal","channel":"UCtX1Pv_xirdNwtwm_8bzZiw","votes":"0","photo":"https:\/\/yt3.ggpht.com\/ytc\/AKedOLRMoGz6syDXRIKhfhRaa3-zN-Z8M5VPRYOFqw=s176-c-k-c0x00ffffff-no-rj","heart":false},{"id_val":"KKW6k0BTcKA","cid":"UgwhJVsQNL1tbNk89Mh4AaABAg","text":"21:00 Blake Baxter - One More Time (Acid Mix) [TRESOR330]","time":"2 weeks ago","author":"Egal Egal","channel":"UCtX1Pv_xirdNwtwm_8bzZiw","votes":"4","photo":"https:\/\/yt3.ggpht.com\/ytc\/AKedOLRMoGz6syDXRIKhfhRaa3-zN-Z8M5VPRYOFqw=s176-c-k-c0x00ffffff-no-rj","heart":false},{"id_val":"KKW6k0BTcKA","cid":"UgwpYfr6X9W1RErAbh14AaABAg","text":"Track Min 17.00???","time":"3 days ago","author":"Federico Fragas","channel":"UCON_lyPlEqTwi3g_Hfsps1Q","votes":"1","photo":"https:\/\/yt3.ggpht.com\/ytc\/AKedOLQ0LKP0lwvh2Dv_WYGX251c-GbLDJfLra9w=s176-c-k-c0x00ffffff-no-rj","heart":false},{"id_val":"KKW6k0BTcKA","cid":"UgzmqLv_QwdrQUhj5op4AaABAg","text":"37:00 DJ K-1 - Erase The Time [DBC4W-010]","time":"2 weeks ago","author":"Egal Egal","channel":"UCtX1Pv_xirdNwtwm_8bzZiw","votes":"0","photo":"https:\/\/yt3.ggpht.com\/ytc\/AKedOLRMoGz6syDXRIKhfhRaa3-zN-Z8M5VPRYOFqw=s176-c-k-c0x00ffffff-no-rj","heart":false},{"id_val":"KKW6k0BTcKA","cid":"UgxjK5JQl8IawpLWfF54AaABAg","text":"43:20 RTS 11.11.11 <3","time":"2 weeks ago","author":"s modest","channel":"UCjNlIoTD1BKVRURODv6FnBg","votes":"0","photo":"https:\/\/yt3.ggpht.com\/ytc\/AKedOLRScz9Tc3Y4qCJNL61YUAY9GkdIGK-sjaIWdNU=s176-c-k-c0x00ffffff-no-rj","heart":false},{"id_val":"KKW6k0BTcKA","cid":"UgzQltWQFq0ubXHeQFR4AaABAg","text":"48:00 Keith Tucker - Face Your Fate (D. Wynn Remix) [ITU2001]","time":"2 weeks ago","author":"Egal Egal","channel":"UCtX1Pv_xirdNwtwm_8bzZiw","votes":"1","photo":"https:\/\/yt3.ggpht.com\/ytc\/AKedOLRMoGz6syDXRIKhfhRaa3-zN-Z8M5VPRYOFqw=s176-c-k-c0x00ffffff-no-rj","heart":false},{"id_val":"KKW6k0BTcKA","cid":"UgzaR3e7sQ1sDzLVHnZ4AaABAg","text":"33:00 Baby Rollen - Metallic Humanoids [GST024]","time":"2 weeks ago","author":"Egal Egal","channel":"UCtX1Pv_xirdNwtwm_8bzZiw","votes":"1","photo":"https:\/\/yt3.ggpht.com\/ytc\/AKedOLRMoGz6syDXRIKhfhRaa3-zN-Z8M5VPRYOFqw=s176-c-k-c0x00ffffff-no-rj","heart":false},{"id_val":"KKW6k0BTcKA","cid":"UgxuXyd75zrLgLifL014AaABAg","text":"25:00 Joakim - Cotton Gun (Kirk Degiorgio Remix) [VER026]","time":"2 weeks ago","author":"Egal Egal","channel":"UCtX1Pv_xirdNwtwm_8bzZiw","votes":"1","photo":"https:\/\/yt3.ggpht.com\/ytc\/AKedOLRMoGz6syDXRIKhfhRaa3-zN-Z8M5VPRYOFqw=s176-c-k-c0x00ffffff-no-rj","heart":false},{"id_val":"KKW6k0BTcKA","cid":"UgwYJ2lnvhmsIeXo7Gh4AaABAg","text":"51:00 Heiko Laux - Move Out [KA62]","time":"2 weeks ago","author":"Egal Egal","channel":"UCtX1Pv_xirdNwtwm_8bzZiw","votes":"0","photo":"https:\/\/yt3.ggpht.com\/ytc\/AKedOLRMoGz6syDXRIKhfhRaa3-zN-Z8M5VPRYOFqw=s176-c-k-c0x00ffffff-no-rj","heart":false},{"id_val":"KKW6k0BTcKA","cid":"UgzL1lkQksZLQzY-DZ14AaABAg","text":"10:17 nicee track!  id anyone ?","time":"2 weeks ago (edited)","author":"Julia Salicova","channel":"UClsFfezlLQ8CXWJ7Vb-IC2w","votes":"4","photo":"https:\/\/yt3.ggpht.com\/ytc\/AKedOLTgXl6oQwLbn-5InRIq3TQqwg4YOnGBbSWmVD9i=s176-c-k-c0x00ffffff-no-rj","heart":false},{"id_val":"KKW6k0BTcKA","cid":"UgwhwRATziVN-dSrp2l4AaABAg","text":"Track @ minute 45???","time":"2 weeks ago (edited)","author":"Taylor Sprague","channel":"UCHu4E9A3B9JxhonTvanxv3g","votes":"2","photo":"https:\/\/yt3.ggpht.com\/ytc\/AKedOLQ_UXxj8QHrWjX-Z2HhiG6hyVq1n8gBjob9PHNI=s176-c-k-c0x00ffffff-no-rj","heart":false},{"id_val":"KKW6k0BTcKA","cid":"Ugy7AWWHwU4RCYAM4lB4AaABAg","text":"Track at 45 please","time":"2 weeks ago","author":"Oliver Watson","channel":"UCTc60zkHO1sFcT0L9BjDdGg","votes":"2","photo":"https:\/\/yt3.ggpht.com\/ytc\/AKedOLTkklPw5wyTU5FQM60yQWH2Sm6yWvV1YEDjoA=s176-c-k-c0x00ffffff-no-rj","heart":false}]