[{"id_val":"O5zExrSjyCg","cid":"UgyU0JfdlojM7jyAw2F4AaABAg","text":"00:00 Sleeparchive \u2013 Elephant Island\r\n04:10 Biemsix \u2013 Clear\r\n07:15 ID - ID\r\n10:56 Shlomi Aber \u2013 Warping\r\n13:34 Kai Van Dongen \u2013 Body Moving\r\n17:02 Solaxid \u2013 Sense of Life (Original mix)\r\n20:56 ID - ID\r\n23:48 Johaness Volk \u2013 Mutable Motor Unit III (Original)\r\n27:42 ID - ID\r\n31:38 Keith Carnal \u2013 Lunar (Original mix)\r\n34:06 Lewis Fautzi \u2013 Stimulated Desorption (Original mix)\r\n37:55 ID - ID\r\n40:02 ID - ID\r\n44:23 Robert Hood \u2013 The Majestic \r\n47:42 Damon Wild & Tim Taylor \u2013 Bang the Acid \u2013 Rebanged! (Echoplex remix)\r\n50:40 ID \u2013 ID\r\n53:22 ID \u2013 ID","time":"3 months ago (edited)","author":"SLUrbex Steve","channel":"UCUlyAY_PMg9T2hiZm23c5Ag","votes":"11","photo":"https:\/\/yt3.ggpht.com\/ytc\/AKedOLQir84rf5N8xSqjrgfiEuWEuM2Gn7tJm8BSVMp_OA=s176-c-k-c0x00ffffff-no-rj","heart":false},{"id_val":"O5zExrSjyCg","cid":"UgzkuwA7z8rHiUGZMzJ4AaABAg","text":"Tracks 3:40 e 46:00 muito top!\ud83d\udd25\ud83d\udd25\ud83d\udc4f\ud83d\udc4f","time":"3 months ago","author":"Jean Soares","channel":"UCxupFElgfHjPaG_hS-8_Cxg","votes":"0","photo":"https:\/\/yt3.ggpht.com\/ytc\/AKedOLQCZmwUvkXOVt6ba_f_nhFIQEhujHuf2pP_Jh8cBQ=s176-c-k-c0x00ffffff-no-rj","heart":false},{"id_val":"O5zExrSjyCg","cid":"UgzkuwA7z8rHiUGZMzJ4AaABAg.9SRoSQr9ue79SnwBi5Bi0m","text":"04:10 Biemsix \u2013 Clear\n46:00 Robert Hood - The Majestic","time":"3 months ago","author":"SLUrbex Steve","channel":"UCUlyAY_PMg9T2hiZm23c5Ag","votes":"1","photo":"https:\/\/yt3.ggpht.com\/ytc\/AKedOLQir84rf5N8xSqjrgfiEuWEuM2Gn7tJm8BSVMp_OA=s176-c-k-c0x00ffffff-no-rj","heart":false},{"id_val":"O5zExrSjyCg","cid":"UgxnnCJ4HM0iILsUKbJ4AaABAg","text":"37:50 got a proper groove.\nMakes me think about \"Kenny Hawkes \u2013 Sleaze Walking\" and \"Blaze feat. Palmer Brown - My Beat (Derrick Carter's Disco Circus Mix)\", though they are house tracks.","time":"3 months ago","author":"Brasidas69","channel":"UCDXLtuPyZaIDOZiEgLkhfig","votes":"0","photo":"https:\/\/yt3.ggpht.com\/ytc\/AKedOLQDJHEckR8_JqGUFpZPJzf5obcXJ8A6tQRspg=s176-c-k-c0x00ffffff-no-rj","heart":false},{"id_val":"O5zExrSjyCg","cid":"UgzHbpbDV52L45Xy1rJ4AaABAg","text":"20:52 this transition blew my mind","time":"3 months ago (edited)","author":"Popeye Regina","channel":"UC8x0EIBA78KPIVoCcm9Z9Zg","votes":"1","photo":"https:\/\/yt3.ggpht.com\/ytc\/AKedOLTFOc3zIPsmLNx8Y9gjw-CkMeQmH7RSwYDsHpOqWw=s176-c-k-c0x00ffffff-no-rj","heart":false},{"id_val":"O5zExrSjyCg","cid":"UgzHbpbDV52L45Xy1rJ4AaABAg.9SRqkJEb9fL9SoltjtB_2z","text":"39:22 this transition blew my mind :P","time":"3 months ago","author":"Paul Hermann","channel":"UCQQixATgvM4eIOQGkDVQksQ","votes":"1","photo":"https:\/\/yt3.ggpht.com\/ytc\/AKedOLRiodBs65QpWkCuTh93J9crIHRlBHKTjTt8LA=s176-c-k-c0x00ffffff-no-rj","heart":false},{"id_val":"O5zExrSjyCg","cid":"UgwMrAcl0ZYHPLTl_QN4AaABAg","text":"21:01 track I.D please?","time":"3 months ago","author":"Popeye Regina","channel":"UC8x0EIBA78KPIVoCcm9Z9Zg","votes":"2","photo":"https:\/\/yt3.ggpht.com\/ytc\/AKedOLTFOc3zIPsmLNx8Y9gjw-CkMeQmH7RSwYDsHpOqWw=s176-c-k-c0x00ffffff-no-rj","heart":false},{"id_val":"O5zExrSjyCg","cid":"Ugz81ZOHHsqAkOxPosN4AaABAg","text":"14:25 please!!!!","time":"3 months ago","author":"Alejandro Castro","channel":"UCJAvH1RYREpWiKdZ__yjrMw","votes":"0","photo":"https:\/\/yt3.ggpht.com\/ytc\/AKedOLQLlqNH6ACiPpPgFg73qZ7yxgqXZ-DINAaFFYC1EQ=s176-c-k-c0x00ffffff-no-rj","heart":false},{"id_val":"O5zExrSjyCg","cid":"Ugyfox9YYi_fOqBUdwh4AaABAg","text":"53:25 ID?!","time":"3 months ago","author":"freddie corless","channel":"UC74OigrnG17tKEYhjN-UCPg","votes":"1","photo":"https:\/\/yt3.ggpht.com\/ytc\/AKedOLSQ34ECzhGobCvNYcRbbAYA58zrk_pG7Jto499zCDXgaUAlXupulB6kZbkOJiNf=s176-c-k-c0x00ffffff-no-rj","heart":false}]