[{"id_val":"r9bqf0ZNGd0","cid":"Ugwpz-MKo-dpAWQsDHV4AaABAg","text":"36:00 Beautiful track! ID?","time":"7 months ago","author":"Rhys Martin","channel":"UCLVgnE3PGWeTbDRGIoWzFeA","votes":"5","photo":"https:\/\/yt3.ggpht.com\/ytc\/AKedOLQ01mNuFYbv28UN8MHqlEgdGbHqVLiDTtDUYQ=s176-c-k-c0x00ffffff-no-rj","heart":false},{"id_val":"r9bqf0ZNGd0","cid":"UgzqVVksh98rY8iTgKV4AaABAg","text":"Track ID min 07:30 ? Great set!","time":"6 months ago","author":"Latorre music","channel":"UC8NBoX9dSufIMpwEdYOEV6A","votes":"0","photo":"https:\/\/yt3.ggpht.com\/ytc\/AKedOLRRAfbqEnJCwUO7DpzCaqfS1H9GyeEwfwrtgJ8g=s176-c-k-c0x00ffffff-no-rj","heart":false},{"id_val":"r9bqf0ZNGd0","cid":"Ugwej1GcQYjw2ttHJWR4AaABAg","text":"Track ID 20:00? \u201cWho\u2019s on the mic\u201d!!!!","time":"4 months ago (edited)","author":"Ian Chamberlain","channel":"UCRyfa7wrQS13Dxi3HERrBvA","votes":"0","photo":"https:\/\/yt3.ggpht.com\/ytc\/AKedOLSgyfbqTz6OHULBbZLf8SnXAqNfCYI35i87Qol0dE8=s176-c-k-c0x00ffffff-no-rj","heart":false},{"id_val":"r9bqf0ZNGd0","cid":"Ugzk13W3xmnPxKh7Cvt4AaABAg","text":"Track ID 30:00 ?","time":"6 months ago","author":"Ian Chamberlain","channel":"UCRyfa7wrQS13Dxi3HERrBvA","votes":"0","photo":"https:\/\/yt3.ggpht.com\/ytc\/AKedOLSgyfbqTz6OHULBbZLf8SnXAqNfCYI35i87Qol0dE8=s176-c-k-c0x00ffffff-no-rj","heart":false},{"id_val":"r9bqf0ZNGd0","cid":"UgyzvRn0KjUfIhUG02p4AaABAg","text":"17:00 track??","time":"7 months ago","author":"Matthew Crisostomo","channel":"UCQhGatddFMhq4LO-g8t_-JQ","votes":"0","photo":"https:\/\/yt3.ggpht.com\/ytc\/AKedOLTTCei5TDGy-puxtMAAW06vuNvqbnQXCxu84GhZ=s176-c-k-c0x00ffffff-no-rj","heart":false},{"id_val":"r9bqf0ZNGd0","cid":"UgzBPK5YjxO7csN19YJ4AaABAg","text":"5:59 ID?","time":"5 months ago","author":"Harry Collins","channel":"UC7P3UeyYSUI2bv_Vq5tTJ6Q","votes":"0","photo":"https:\/\/yt3.ggpht.com\/ytc\/AKedOLTrCv_3lvoXhfjf1MDMoQIBbMhNhZlcH-blZNHN=s176-c-k-c0x00ffffff-no-rj","heart":false}]