[{"id_val":"zPb8N5q1gjM","cid":"Ugw609B8s7SscVCuCWh4AaABAg","text":"30:00 \u043e \u0431\u043e\u0433\u0438, \u0447\u0442\u043e \u0437\u0430 \u0442\u0440\u0435\u043a? \u0412\u0441\u0435\u0437\u043d\u0430\u044e\u0449\u0438\u0435 \u043e\u0441\u0432\u0435\u0442\u0438\u0442\u0435 \u043f\u0443\u0442\u044c","time":"4 weeks ago","author":"\u0414\u043c\u0438\u0442\u0440\u0438\u0439 \u041b\u0443\u043a\u0430\u0448\u0435\u043d\u043a\u043e","channel":"UCia7bmgYBQLh-aGWAZc1U9g","votes":"2","photo":"https:\/\/yt3.ggpht.com\/ytc\/AKedOLRiPJc9aEoWCmGrl_1zJs2fvLFqey6hQrbp9lpLXQ=s176-c-k-c0x00ffffff-no-rj","heart":false},{"id_val":"zPb8N5q1gjM","cid":"UgyoeZuD4xNY_tZxtSV4AaABAg","text":"16:23 what is this song!?","time":"4 weeks ago","author":"Jonathon Famularo","channel":"UCNtx5UKA2qRhkSM6dCrT1xg","votes":"10","photo":"https:\/\/yt3.ggpht.com\/ytc\/AKedOLTu-WXOrSDNBbUbCwzaX8c8bdHIQwkIaA8V=s176-c-k-c0x00ffffff-no-rj","heart":false},{"id_val":"zPb8N5q1gjM","cid":"Ugz7CLGmZdCeo4aKwcR4AaABAg","text":"42:39 - kung fu bass detected","time":"4 hours ago","author":"Salabai Viacheslav","channel":"UCxNI_O2jpejfUVyTEJ5vFxw","votes":"0","photo":"https:\/\/yt3.ggpht.com\/ytc\/AKedOLRbZHXe8kLzXeYvMq7nXoRpUl-Z3iekXWgMsY6Lig=s176-c-k-c0x00ffffff-no-rj","heart":false},{"id_val":"zPb8N5q1gjM","cid":"Ugy-MIXe10tkwCD9Hyx4AaABAg","text":"16:30 track id ?","time":"4 weeks ago","author":"Sabrina Brunone","channel":"UCudJ_Pj-XxTX07QC5i306Gg","votes":"0","photo":"https:\/\/yt3.ggpht.com\/TZomQf52-MG-qeOt30eLKy5y2aJApcZKyLFXXWzQbH0_J6Gtg9_37eUQFFwPCkOTaSekYxZBwQ=s176-c-k-c0x00ffffff-no-rj","heart":false}]